{
    "13TeV_MB_default": {
        "histoMtScaleFactor": {
            "113": 0.87,
            "223": 0.572,
            "331": 0.4
        },
        "111_pt": "( x*(55.4505*TMath::Exp(-(TMath::Sqrt(x*x+0.134977*0.134977)-0.134977)/0.14849)+2.93224*TMath::Power(1+(x*x)/(0.64965*0.64965*2.97448),-2.97448)) )",
        "221_pt": "( x*(55.4505*TMath::Exp(-(TMath::Sqrt(x*x+0.134977*0.134977)-0.134977)/0.14849)+2.93224*TMath::Power(1+(x*x)/(0.64965*0.64965*2.97448),-2.97448)) ) * ((0.554328*1.)+(176.93*(-0.00310177*TMath::Power(1.+((x/0.993569)*(x/0.993569)),-(0.480035)))))/(1.+(-0.00310177*TMath::Power(1.+((x/0.993569)*(x/0.993569)),-(0.480035))))",
        "333_pt": "(x*0.162735*TMath::Power(TMath::Exp(-0.455874*x-TMath::Abs(-0.0589095)*x*x)+x/1.30284,-5.7907))",
        "443_pt": "x*3.76783e-05/TMath::Power((1+TMath::Power(x/4.06472,2.0)),3.03429)",
        "321_pt": "1.2778632*x*7.70776*TMath::Power(TMath::Exp(-0.618249*x-TMath::Abs(3.16962e-09)*x*x)+x/1.02821,-5.47764)",
        "2212_pt": "1.2778632*x*1.4891*TMath::Power(TMath::Exp(-0.4799*x-TMath::Abs(0.0225614)*x*x)+x/1.6315,-6.82731)"
    },
    "13TeV_MB_etaup": {
        "histoMtScaleFactor": {
            "113": 0.87,
            "223": 0.572,
            "331": 0.4
        },
        "111_pt": "( x*(55.4505*TMath::Exp(-(TMath::Sqrt(x*x+0.134977*0.134977)-0.134977)/0.14849)+2.93224*TMath::Power(1+(x*x)/(0.64965*0.64965*2.97448),-2.97448)) )",
        "221_pt": "( x*(55.4505*TMath::Exp(-(TMath::Sqrt(x*x+0.134977*0.134977)-0.134977)/0.14849)+2.93224*TMath::Power(1+(x*x)/(0.64965*0.64965*2.97448),-2.97448)) ) * ((0.609299*1.)+(185.522*(-0.00325225*TMath::Power(1.+((x/0.861816)*(x/0.861816)),-(0.384348)))))/(1.+(-0.00325225*TMath::Power(1.+((x/0.861816)*(x/0.861816)),-(0.384348))))",
        "333_pt": "(x*0.162735*TMath::Power(TMath::Exp(-0.455874*x-TMath::Abs(-0.0589095)*x*x)+x/1.30284,-5.7907))",
        "443_pt": "x*3.76783e-05/TMath::Power((1+TMath::Power(x/4.06472,2.0)),3.03429)",
        "321_pt": "1.2778632*x*7.70776*TMath::Power(TMath::Exp(-0.618249*x-TMath::Abs(3.16962e-09)*x*x)+x/1.02821,-5.47764)",
        "2212_pt": "1.2778632*x*1.4891*TMath::Power(TMath::Exp(-0.4799*x-TMath::Abs(0.0225614)*x*x)+x/1.6315,-6.82731)"
    },
    "13TeV_MB_etadown": {
        "histoMtScaleFactor": {
            "113": 0.87,
            "223": 0.572,
            "331": 0.4
        },
        "111_pt": "( x*(55.4505*TMath::Exp(-(TMath::Sqrt(x*x+0.134977*0.134977)-0.134977)/0.14849)+2.93224*TMath::Power(1+(x*x)/(0.64965*0.64965*2.97448),-2.97448)) )",
        "221_pt": "( x*(55.4505*TMath::Exp(-(TMath::Sqrt(x*x+0.134977*0.134977)-0.134977)/0.14849)+2.93224*TMath::Power(1+(x*x)/(0.64965*0.64965*2.97448),-2.97448)) ) * ((0.509237*1.)+(169.821*(-0.00297709*TMath::Power(1.+((x/1.1418)*(x/1.1418)),-(0.59809)))))/(1.+(-0.00297709*TMath::Power(1.+((x/1.1418)*(x/1.1418)),-(0.59809))))",
        "333_pt": "(x*0.162735*TMath::Power(TMath::Exp(-0.455874*x-TMath::Abs(-0.0589095)*x*x)+x/1.30284,-5.7907))",
        "443_pt": "x*3.76783e-05/TMath::Power((1+TMath::Power(x/4.06472,2.0)),3.03429)",
        "321_pt": "1.2778632*x*7.70776*TMath::Power(TMath::Exp(-0.618249*x-TMath::Abs(3.16962e-09)*x*x)+x/1.02821,-5.47764)",
        "2212_pt": "1.2778632*x*1.4891*TMath::Power(TMath::Exp(-0.4799*x-TMath::Abs(0.0225614)*x*x)+x/1.6315,-6.82731)"
    },
    "13TeV_MB_etaextra": {
        "histoMtScaleFactor": {
            "113": 0.87,
            "223": 0.572,
            "331": 0.4
        },
        "111_pt": "( x*(55.4505*TMath::Exp(-(TMath::Sqrt(x*x+0.134977*0.134977)-0.134977)/0.14849)+2.93224*TMath::Power(1+(x*x)/(0.64965*0.64965*2.97448),-2.97448)) )",
        "221_pt": "( x*(55.4505*TMath::Exp(-(TMath::Sqrt(x*x+0.134977*0.134977)-0.134977)/0.14849)+2.93224*TMath::Power(1+(x*x)/(0.64965*0.64965*2.97448),-2.97448)) ) * ((0.591597*1.)+(179.421*(-0.00314491*TMath::Power(1.+((x/0.887987)*(x/0.887987)),-(0.374403)))))/(1.+(-0.00314491*TMath::Power(1.+((x/0.887987)*(x/0.887987)),-(0.374403))))",
        "333_pt": "(x*0.162735*TMath::Power(TMath::Exp(-0.455874*x-TMath::Abs(-0.0589095)*x*x)+x/1.30284,-5.7907))",
        "443_pt": "x*3.76783e-05/TMath::Power((1+TMath::Power(x/4.06472,2.0)),3.03429)",
        "321_pt": "1.2778632*x*7.70776*TMath::Power(TMath::Exp(-0.618249*x-TMath::Abs(3.16962e-09)*x*x)+x/1.02821,-5.47764)",
        "2212_pt": "1.2778632*x*1.4891*TMath::Power(TMath::Exp(-0.4799*x-TMath::Abs(0.0225614)*x*x)+x/1.6315,-6.82731)"
    },
    "13TeV_MB_pi0up_eta": {
        "histoMtScaleFactor": {
            "113": 0.87,
            "223": 0.572,
            "331": 0.4
        },
        "111_pt": "( x*(55.4505*TMath::Exp(-(TMath::Sqrt(x*x+0.134977*0.134977)-0.134977)/0.14849)+2.93224*TMath::Power(1+(x*x)/(0.64965*0.64965*2.97448),-2.97448)) )",
        "221_pt": "( x*(86.1264*TMath::Exp(-(TMath::Sqrt(x*x+0.134977*0.134977)-0.134977)/0.13135)+3.52458*TMath::Power(1+(x*x)/(0.627488*0.627488*2.95669),-2.95669)) ) * ((0.554328*1.)+(176.93*(-0.00310177*TMath::Power(1.+((x/0.993569)*(x/0.993569)),-(0.480035)))))/(1.+(-0.00310177*TMath::Power(1.+((x/0.993569)*(x/0.993569)),-(0.480035))))",
        "333_pt": "(x*0.162735*TMath::Power(TMath::Exp(-0.455874*x-TMath::Abs(-0.0589095)*x*x)+x/1.30284,-5.7907))",
        "443_pt": "x*3.76783e-05/TMath::Power((1+TMath::Power(x/4.06472,2.0)),3.03429)",
        "321_pt": "1.2778632*x*7.70776*TMath::Power(TMath::Exp(-0.618249*x-TMath::Abs(3.16962e-09)*x*x)+x/1.02821,-5.47764)",
        "2212_pt": "1.2778632*x*1.4891*TMath::Power(TMath::Exp(-0.4799*x-TMath::Abs(0.0225614)*x*x)+x/1.6315,-6.82731)"
    },
    "13TeV_MB_pi0up_etaup": {
        "histoMtScaleFactor": {
            "113": 0.87,
            "223": 0.572,
            "331": 0.4
        },
        "111_pt": "( x*(55.4505*TMath::Exp(-(TMath::Sqrt(x*x+0.134977*0.134977)-0.134977)/0.14849)+2.93224*TMath::Power(1+(x*x)/(0.64965*0.64965*2.97448),-2.97448)) )",
        "221_pt": "( x*(86.1264*TMath::Exp(-(TMath::Sqrt(x*x+0.134977*0.134977)-0.134977)/0.13135)+3.52458*TMath::Power(1+(x*x)/(0.627488*0.627488*2.95669),-2.95669)) ) * ((0.609299*1.)+(185.522*(-0.00325225*TMath::Power(1.+((x/0.861816)*(x/0.861816)),-(0.384348)))))/(1.+(-0.00325225*TMath::Power(1.+((x/0.861816)*(x/0.861816)),-(0.384348))))",
        "333_pt": "(x*0.162735*TMath::Power(TMath::Exp(-0.455874*x-TMath::Abs(-0.0589095)*x*x)+x/1.30284,-5.7907))",
        "443_pt": "x*3.76783e-05/TMath::Power((1+TMath::Power(x/4.06472,2.0)),3.03429)",
        "321_pt": "1.2778632*x*7.70776*TMath::Power(TMath::Exp(-0.618249*x-TMath::Abs(3.16962e-09)*x*x)+x/1.02821,-5.47764)",
        "2212_pt": "1.2778632*x*1.4891*TMath::Power(TMath::Exp(-0.4799*x-TMath::Abs(0.0225614)*x*x)+x/1.6315,-6.82731)"
    },
    "13TeV_MB_pi0up_etadown": {
        "histoMtScaleFactor": {
            "113": 0.87,
            "223": 0.572,
            "331": 0.4
        },
        "111_pt": "( x*(55.4505*TMath::Exp(-(TMath::Sqrt(x*x+0.134977*0.134977)-0.134977)/0.14849)+2.93224*TMath::Power(1+(x*x)/(0.64965*0.64965*2.97448),-2.97448)) )",
        "221_pt": "( x*(86.1264*TMath::Exp(-(TMath::Sqrt(x*x+0.134977*0.134977)-0.134977)/0.13135)+3.52458*TMath::Power(1+(x*x)/(0.627488*0.627488*2.95669),-2.95669)) ) * ((0.509237*1.)+(169.821*(-0.00297709*TMath::Power(1.+((x/1.1418)*(x/1.1418)),-(0.59809)))))/(1.+(-0.00297709*TMath::Power(1.+((x/1.1418)*(x/1.1418)),-(0.59809))))",
        "333_pt": "(x*0.162735*TMath::Power(TMath::Exp(-0.455874*x-TMath::Abs(-0.0589095)*x*x)+x/1.30284,-5.7907))",
        "443_pt": "x*3.76783e-05/TMath::Power((1+TMath::Power(x/4.06472,2.0)),3.03429)",
        "321_pt": "1.2778632*x*7.70776*TMath::Power(TMath::Exp(-0.618249*x-TMath::Abs(3.16962e-09)*x*x)+x/1.02821,-5.47764)",
        "2212_pt": "1.2778632*x*1.4891*TMath::Power(TMath::Exp(-0.4799*x-TMath::Abs(0.0225614)*x*x)+x/1.6315,-6.82731)"
    },
    "13TeV_MB_pi0down_eta": {
        "histoMtScaleFactor": {
            "113": 0.87,
            "223": 0.572,
            "331": 0.4
        },
        "111_pt": "( x*(55.4505*TMath::Exp(-(TMath::Sqrt(x*x+0.134977*0.134977)-0.134977)/0.14849)+2.93224*TMath::Power(1+(x*x)/(0.64965*0.64965*2.97448),-2.97448)) )",
        "221_pt": "( x*(41.9814*TMath::Exp(-(TMath::Sqrt(x*x+0.134977*0.134977)-0.134977)/0.159935)+2.55206*TMath::Power(1+(x*x)/(0.66629*0.66629*2.99049),-2.99049)) ) * ((0.554328*1.)+(176.93*(-0.00310177*TMath::Power(1.+((x/0.993569)*(x/0.993569)),-(0.480035)))))/(1.+(-0.00310177*TMath::Power(1.+((x/0.993569)*(x/0.993569)),-(0.480035))))",
        "333_pt": "(x*0.162735*TMath::Power(TMath::Exp(-0.455874*x-TMath::Abs(-0.0589095)*x*x)+x/1.30284,-5.7907))",
        "443_pt": "x*3.76783e-05/TMath::Power((1+TMath::Power(x/4.06472,2.0)),3.03429)",
        "321_pt": "1.2778632*x*7.70776*TMath::Power(TMath::Exp(-0.618249*x-TMath::Abs(3.16962e-09)*x*x)+x/1.02821,-5.47764)",
        "2212_pt": "1.2778632*x*1.4891*TMath::Power(TMath::Exp(-0.4799*x-TMath::Abs(0.0225614)*x*x)+x/1.6315,-6.82731)"
    },
    "13TeV_MB_pi0down_etaup": {
        "histoMtScaleFactor": {
            "113": 0.87,
            "223": 0.572,
            "331": 0.4
        },
        "111_pt": "( x*(55.4505*TMath::Exp(-(TMath::Sqrt(x*x+0.134977*0.134977)-0.134977)/0.14849)+2.93224*TMath::Power(1+(x*x)/(0.64965*0.64965*2.97448),-2.97448)) )",
        "221_pt": "( x*(41.9814*TMath::Exp(-(TMath::Sqrt(x*x+0.134977*0.134977)-0.134977)/0.159935)+2.55206*TMath::Power(1+(x*x)/(0.66629*0.66629*2.99049),-2.99049)) ) * ((0.609299*1.)+(185.522*(-0.00325225*TMath::Power(1.+((x/0.861816)*(x/0.861816)),-(0.384348)))))/(1.+(-0.00325225*TMath::Power(1.+((x/0.861816)*(x/0.861816)),-(0.384348))))",
        "333_pt": "(x*0.162735*TMath::Power(TMath::Exp(-0.455874*x-TMath::Abs(-0.0589095)*x*x)+x/1.30284,-5.7907))",
        "443_pt": "x*3.76783e-05/TMath::Power((1+TMath::Power(x/4.06472,2.0)),3.03429)",
        "321_pt": "1.2778632*x*7.70776*TMath::Power(TMath::Exp(-0.618249*x-TMath::Abs(3.16962e-09)*x*x)+x/1.02821,-5.47764)",
        "2212_pt": "1.2778632*x*1.4891*TMath::Power(TMath::Exp(-0.4799*x-TMath::Abs(0.0225614)*x*x)+x/1.6315,-6.82731)"
    },
    "13TeV_MB_pi0down_etadown": {
        "histoMtScaleFactor": {
            "113": 0.87,
            "223": 0.572,
            "331": 0.4
        },
        "111_pt": "( x*(55.4505*TMath::Exp(-(TMath::Sqrt(x*x+0.134977*0.134977)-0.134977)/0.14849)+2.93224*TMath::Power(1+(x*x)/(0.64965*0.64965*2.97448),-2.97448)) )",
        "221_pt": "( x*(41.9814*TMath::Exp(-(TMath::Sqrt(x*x+0.134977*0.134977)-0.134977)/0.159935)+2.55206*TMath::Power(1+(x*x)/(0.66629*0.66629*2.99049),-2.99049)) ) * ((0.509237*1.)+(169.821*(-0.00297709*TMath::Power(1.+((x/1.1418)*(x/1.1418)),-(0.59809)))))/(1.+(-0.00297709*TMath::Power(1.+((x/1.1418)*(x/1.1418)),-(0.59809))))",
        "333_pt": "(x*0.162735*TMath::Power(TMath::Exp(-0.455874*x-TMath::Abs(-0.0589095)*x*x)+x/1.30284,-5.7907))",
        "443_pt": "x*3.76783e-05/TMath::Power((1+TMath::Power(x/4.06472,2.0)),3.03429)",
        "321_pt": "1.2778632*x*7.70776*TMath::Power(TMath::Exp(-0.618249*x-TMath::Abs(3.16962e-09)*x*x)+x/1.02821,-5.47764)",
        "2212_pt": "1.2778632*x*1.4891*TMath::Power(TMath::Exp(-0.4799*x-TMath::Abs(0.0225614)*x*x)+x/1.6315,-6.82731)"
    },
    "13TeV_MB_phiup": {
        "histoMtScaleFactor": {
            "113": 0.87,
            "223": 0.572,
            "331": 0.4
        },
        "111_pt": "( x*(55.4505*TMath::Exp(-(TMath::Sqrt(x*x+0.134977*0.134977)-0.134977)/0.14849)+2.93224*TMath::Power(1+(x*x)/(0.64965*0.64965*2.97448),-2.97448)) )",
        "221_pt": "( x*(55.4505*TMath::Exp(-(TMath::Sqrt(x*x+0.134977*0.134977)-0.134977)/0.14849)+2.93224*TMath::Power(1+(x*x)/(0.64965*0.64965*2.97448),-2.97448)) ) * ((0.554328*1.)+(176.93*(-0.00310177*TMath::Power(1.+((x/0.993569)*(x/0.993569)),-(0.480035)))))/(1.+(-0.00310177*TMath::Power(1.+((x/0.993569)*(x/0.993569)),-(0.480035))))",
        "333_pt": "1.1*(x*0.162735*TMath::Power(TMath::Exp(-0.455874*x-TMath::Abs(-0.0589095)*x*x)+x/1.30284,-5.7907))",
        "443_pt": "x*3.76783e-05/TMath::Power((1+TMath::Power(x/4.06472,2.0)),3.03429)",
        "321_pt": "1.2778632*x*7.70776*TMath::Power(TMath::Exp(-0.618249*x-TMath::Abs(3.16962e-09)*x*x)+x/1.02821,-5.47764)",
        "2212_pt": "1.2778632*x*1.4891*TMath::Power(TMath::Exp(-0.4799*x-TMath::Abs(0.0225614)*x*x)+x/1.6315,-6.82731)"
    },
    "13TeV_MB_phidown": {
        "histoMtScaleFactor": {
            "113": 0.87,
            "223": 0.572,
            "331": 0.4
        },
        "111_pt": "( x*(55.4505*TMath::Exp(-(TMath::Sqrt(x*x+0.134977*0.134977)-0.134977)/0.14849)+2.93224*TMath::Power(1+(x*x)/(0.64965*0.64965*2.97448),-2.97448)) )",
        "221_pt": "( x*(55.4505*TMath::Exp(-(TMath::Sqrt(x*x+0.134977*0.134977)-0.134977)/0.14849)+2.93224*TMath::Power(1+(x*x)/(0.64965*0.64965*2.97448),-2.97448)) ) * ((0.554328*1.)+(176.93*(-0.00310177*TMath::Power(1.+((x/0.993569)*(x/0.993569)),-(0.480035)))))/(1.+(-0.00310177*TMath::Power(1.+((x/0.993569)*(x/0.993569)),-(0.480035))))",
        "333_pt": "0.9*(x*0.162735*TMath::Power(TMath::Exp(-0.455874*x-TMath::Abs(-0.0589095)*x*x)+x/1.30284,-5.7907))",
        "443_pt": "x*3.76783e-05/TMath::Power((1+TMath::Power(x/4.06472,2.0)),3.03429)",
        "321_pt": "1.2778632*x*7.70776*TMath::Power(TMath::Exp(-0.618249*x-TMath::Abs(3.16962e-09)*x*x)+x/1.02821,-5.47764)",
        "2212_pt": "1.2778632*x*1.4891*TMath::Power(TMath::Exp(-0.4799*x-TMath::Abs(0.0225614)*x*x)+x/1.6315,-6.82731)"
    },
    "13TeV_MB_etapup": {
        "histoMtScaleFactor": {
            "113": 0.87,
            "223": 0.572,
            "331": 0.48
        },
        "111_pt": "( x*(55.4505*TMath::Exp(-(TMath::Sqrt(x*x+0.134977*0.134977)-0.134977)/0.14849)+2.93224*TMath::Power(1+(x*x)/(0.64965*0.64965*2.97448),-2.97448)) )",
        "221_pt": "( x*(55.4505*TMath::Exp(-(TMath::Sqrt(x*x+0.134977*0.134977)-0.134977)/0.14849)+2.93224*TMath::Power(1+(x*x)/(0.64965*0.64965*2.97448),-2.97448)) ) * ((0.554328*1.)+(176.93*(-0.00310177*TMath::Power(1.+((x/0.993569)*(x/0.993569)),-(0.480035)))))/(1.+(-0.00310177*TMath::Power(1.+((x/0.993569)*(x/0.993569)),-(0.480035))))",
        "333_pt": "(x*0.162735*TMath::Power(TMath::Exp(-0.455874*x-TMath::Abs(-0.0589095)*x*x)+x/1.30284,-5.7907))",
        "443_pt": "x*3.76783e-05/TMath::Power((1+TMath::Power(x/4.06472,2.0)),3.03429)",
        "321_pt": "1.2778632*x*7.70776*TMath::Power(TMath::Exp(-0.618249*x-TMath::Abs(3.16962e-09)*x*x)+x/1.02821,-5.47764)",
        "2212_pt": "1.2778632*x*1.4891*TMath::Power(TMath::Exp(-0.4799*x-TMath::Abs(0.0225614)*x*x)+x/1.6315,-6.82731)"
    },
    "13TeV_MB_etapdown": {
        "histoMtScaleFactor": {
            "113": 0.87,
            "223": 0.572,
            "331": 0.32
        },
        "111_pt": "( x*(55.4505*TMath::Exp(-(TMath::Sqrt(x*x+0.134977*0.134977)-0.134977)/0.14849)+2.93224*TMath::Power(1+(x*x)/(0.64965*0.64965*2.97448),-2.97448)) )",
        "221_pt": "( x*(55.4505*TMath::Exp(-(TMath::Sqrt(x*x+0.134977*0.134977)-0.134977)/0.14849)+2.93224*TMath::Power(1+(x*x)/(0.64965*0.64965*2.97448),-2.97448)) ) * ((0.554328*1.)+(176.93*(-0.00310177*TMath::Power(1.+((x/0.993569)*(x/0.993569)),-(0.480035)))))/(1.+(-0.00310177*TMath::Power(1.+((x/0.993569)*(x/0.993569)),-(0.480035))))",
        "333_pt": "(x*0.162735*TMath::Power(TMath::Exp(-0.455874*x-TMath::Abs(-0.0589095)*x*x)+x/1.30284,-5.7907))",
        "443_pt": "x*3.76783e-05/TMath::Power((1+TMath::Power(x/4.06472,2.0)),3.03429)",
        "321_pt": "1.2778632*x*7.70776*TMath::Power(TMath::Exp(-0.618249*x-TMath::Abs(3.16962e-09)*x*x)+x/1.02821,-5.47764)",
        "2212_pt": "1.2778632*x*1.4891*TMath::Power(TMath::Exp(-0.4799*x-TMath::Abs(0.0225614)*x*x)+x/1.6315,-6.82731)"
    },
    "13TeV_MB_rhoup": {
        "histoMtScaleFactor": {
            "113": 1.044,
            "223": 0.572,
            "331": 0.4
        },
        "111_pt": "( x*(55.4505*TMath::Exp(-(TMath::Sqrt(x*x+0.134977*0.134977)-0.134977)/0.14849)+2.93224*TMath::Power(1+(x*x)/(0.64965*0.64965*2.97448),-2.97448)) )",
        "221_pt": "( x*(55.4505*TMath::Exp(-(TMath::Sqrt(x*x+0.134977*0.134977)-0.134977)/0.14849)+2.93224*TMath::Power(1+(x*x)/(0.64965*0.64965*2.97448),-2.97448)) ) * ((0.554328*1.)+(176.93*(-0.00310177*TMath::Power(1.+((x/0.993569)*(x/0.993569)),-(0.480035)))))/(1.+(-0.00310177*TMath::Power(1.+((x/0.993569)*(x/0.993569)),-(0.480035))))",
        "333_pt": "(x*0.162735*TMath::Power(TMath::Exp(-0.455874*x-TMath::Abs(-0.0589095)*x*x)+x/1.30284,-5.7907))",
        "443_pt": "x*3.76783e-05/TMath::Power((1+TMath::Power(x/4.06472,2.0)),3.03429)",
        "321_pt": "1.2778632*x*7.70776*TMath::Power(TMath::Exp(-0.618249*x-TMath::Abs(3.16962e-09)*x*x)+x/1.02821,-5.47764)",
        "2212_pt": "1.2778632*x*1.4891*TMath::Power(TMath::Exp(-0.4799*x-TMath::Abs(0.0225614)*x*x)+x/1.6315,-6.82731)"
    },
    "13TeV_MB_rhodown": {
        "histoMtScaleFactor": {
            "113": 0.696,
            "223": 0.572,
            "331": 0.4
        },
        "111_pt": "( x*(55.4505*TMath::Exp(-(TMath::Sqrt(x*x+0.134977*0.134977)-0.134977)/0.14849)+2.93224*TMath::Power(1+(x*x)/(0.64965*0.64965*2.97448),-2.97448)) )",
        "221_pt": "( x*(55.4505*TMath::Exp(-(TMath::Sqrt(x*x+0.134977*0.134977)-0.134977)/0.14849)+2.93224*TMath::Power(1+(x*x)/(0.64965*0.64965*2.97448),-2.97448)) ) * ((0.554328*1.)+(176.93*(-0.00310177*TMath::Power(1.+((x/0.993569)*(x/0.993569)),-(0.480035)))))/(1.+(-0.00310177*TMath::Power(1.+((x/0.993569)*(x/0.993569)),-(0.480035))))",
        "333_pt": "(x*0.162735*TMath::Power(TMath::Exp(-0.455874*x-TMath::Abs(-0.0589095)*x*x)+x/1.30284,-5.7907))",
        "443_pt": "x*3.76783e-05/TMath::Power((1+TMath::Power(x/4.06472,2.0)),3.03429)",
        "321_pt": "1.2778632*x*7.70776*TMath::Power(TMath::Exp(-0.618249*x-TMath::Abs(3.16962e-09)*x*x)+x/1.02821,-5.47764)",
        "2212_pt": "1.2778632*x*1.4891*TMath::Power(TMath::Exp(-0.4799*x-TMath::Abs(0.0225614)*x*x)+x/1.6315,-6.82731)"
    },
    "13TeV_MB_omegaup": {
        "histoMtScaleFactor": {
            "113": 0.87,
            "223": 0.6864,
            "331": 0.4
        },
        "111_pt": "( x*(55.4505*TMath::Exp(-(TMath::Sqrt(x*x+0.134977*0.134977)-0.134977)/0.14849)+2.93224*TMath::Power(1+(x*x)/(0.64965*0.64965*2.97448),-2.97448)) )",
        "221_pt": "( x*(55.4505*TMath::Exp(-(TMath::Sqrt(x*x+0.134977*0.134977)-0.134977)/0.14849)+2.93224*TMath::Power(1+(x*x)/(0.64965*0.64965*2.97448),-2.97448)) ) * ((0.554328*1.)+(176.93*(-0.00310177*TMath::Power(1.+((x/0.993569)*(x/0.993569)),-(0.480035)))))/(1.+(-0.00310177*TMath::Power(1.+((x/0.993569)*(x/0.993569)),-(0.480035))))",
        "333_pt": "(x*0.162735*TMath::Power(TMath::Exp(-0.455874*x-TMath::Abs(-0.0589095)*x*x)+x/1.30284,-5.7907))",
        "443_pt": "x*3.76783e-05/TMath::Power((1+TMath::Power(x/4.06472,2.0)),3.03429)",
        "321_pt": "1.2778632*x*7.70776*TMath::Power(TMath::Exp(-0.618249*x-TMath::Abs(3.16962e-09)*x*x)+x/1.02821,-5.47764)",
        "2212_pt": "1.2778632*x*1.4891*TMath::Power(TMath::Exp(-0.4799*x-TMath::Abs(0.0225614)*x*x)+x/1.6315,-6.82731)"
    },
    "13TeV_MB_omegadown": {
        "histoMtScaleFactor": {
            "113": 0.87,
            "223": 0.4576,
            "331": 0.4
        },
        "111_pt": "( x*(55.4505*TMath::Exp(-(TMath::Sqrt(x*x+0.134977*0.134977)-0.134977)/0.14849)+2.93224*TMath::Power(1+(x*x)/(0.64965*0.64965*2.97448),-2.97448)) )",
        "221_pt": "( x*(55.4505*TMath::Exp(-(TMath::Sqrt(x*x+0.134977*0.134977)-0.134977)/0.14849)+2.93224*TMath::Power(1+(x*x)/(0.64965*0.64965*2.97448),-2.97448)) ) * ((0.554328*1.)+(176.93*(-0.00310177*TMath::Power(1.+((x/0.993569)*(x/0.993569)),-(0.480035)))))/(1.+(-0.00310177*TMath::Power(1.+((x/0.993569)*(x/0.993569)),-(0.480035))))",
        "333_pt": "(x*0.162735*TMath::Power(TMath::Exp(-0.455874*x-TMath::Abs(-0.0589095)*x*x)+x/1.30284,-5.7907))",
        "443_pt": "x*3.76783e-05/TMath::Power((1+TMath::Power(x/4.06472,2.0)),3.03429)",
        "321_pt": "1.2778632*x*7.70776*TMath::Power(TMath::Exp(-0.618249*x-TMath::Abs(3.16962e-09)*x*x)+x/1.02821,-5.47764)",
        "2212_pt": "1.2778632*x*1.4891*TMath::Power(TMath::Exp(-0.4799*x-TMath::Abs(0.0225614)*x*x)+x/1.6315,-6.82731)"
    },
    "13TeV_MB_jpsiup": {
        "histoMtScaleFactor": {
            "113": 0.87,
            "223": 0.572,
            "331": 0.4
        },
        "111_pt": "( x*(55.4505*TMath::Exp(-(TMath::Sqrt(x*x+0.134977*0.134977)-0.134977)/0.14849)+2.93224*TMath::Power(1+(x*x)/(0.64965*0.64965*2.97448),-2.97448)) )",
        "221_pt": "( x*(55.4505*TMath::Exp(-(TMath::Sqrt(x*x+0.134977*0.134977)-0.134977)/0.14849)+2.93224*TMath::Power(1+(x*x)/(0.64965*0.64965*2.97448),-2.97448)) ) * ((0.554328*1.)+(176.93*(-0.00310177*TMath::Power(1.+((x/0.993569)*(x/0.993569)),-(0.480035)))))/(1.+(-0.00310177*TMath::Power(1.+((x/0.993569)*(x/0.993569)),-(0.480035))))",
        "333_pt": "(x*0.162735*TMath::Power(TMath::Exp(-0.455874*x-TMath::Abs(-0.0589095)*x*x)+x/1.30284,-5.7907))",
        "443_pt": "x*4.1893e-05/TMath::Power((1+TMath::Power(x/4.01254,2.0)),3.00288)",
        "321_pt": "1.2778632*x*7.70776*TMath::Power(TMath::Exp(-0.618249*x-TMath::Abs(3.16962e-09)*x*x)+x/1.02821,-5.47764)",
        "2212_pt": "1.2778632*x*1.4891*TMath::Power(TMath::Exp(-0.4799*x-TMath::Abs(0.0225614)*x*x)+x/1.6315,-6.82731)"
    },
    "13TeV_MB_jpsidown": {
        "histoMtScaleFactor": {
            "113": 0.87,
            "223": 0.572,
            "331": 0.4
        },
        "111_pt": "( x*(55.4505*TMath::Exp(-(TMath::Sqrt(x*x+0.134977*0.134977)-0.134977)/0.14849)+2.93224*TMath::Power(1+(x*x)/(0.64965*0.64965*2.97448),-2.97448)) )",
        "221_pt": "( x*(55.4505*TMath::Exp(-(TMath::Sqrt(x*x+0.134977*0.134977)-0.134977)/0.14849)+2.93224*TMath::Power(1+(x*x)/(0.64965*0.64965*2.97448),-2.97448)) ) * ((0.554328*1.)+(176.93*(-0.00310177*TMath::Power(1.+((x/0.993569)*(x/0.993569)),-(0.480035)))))/(1.+(-0.00310177*TMath::Power(1.+((x/0.993569)*(x/0.993569)),-(0.480035))))",
        "333_pt": "(x*0.162735*TMath::Power(TMath::Exp(-0.455874*x-TMath::Abs(-0.0589095)*x*x)+x/1.30284,-5.7907))",
        "443_pt": "x*3.34811e-05/TMath::Power((1+TMath::Power(x/4.12933,2.0)),3.07406)",
        "321_pt": "1.2778632*x*7.70776*TMath::Power(TMath::Exp(-0.618249*x-TMath::Abs(3.16962e-09)*x*x)+x/1.02821,-5.47764)",
        "2212_pt": "1.2778632*x*1.4891*TMath::Power(TMath::Exp(-0.4799*x-TMath::Abs(0.0225614)*x*x)+x/1.6315,-6.82731)"
    },
    "13TeV_MB_16_jpsidefault": {
        "histoMtScaleFactor": {
            "113": 0.87,
            "223": 0.572,
            "331": 0.4
        },
        "111_pt": "( x*(55.4505*TMath::Exp(-(TMath::Sqrt(x*x+0.134977*0.134977)-0.134977)/0.14849)+2.93224*TMath::Power(1+(x*x)/(0.64965*0.64965*2.97448),-2.97448)) )",
        "221_pt": "( x*(55.4505*TMath::Exp(-(TMath::Sqrt(x*x+0.134977*0.134977)-0.134977)/0.14849)+2.93224*TMath::Power(1+(x*x)/(0.64965*0.64965*2.97448),-2.97448)) ) * ((0.554328*1.)+(176.93*(-0.00310177*TMath::Power(1.+((x/0.993569)*(x/0.993569)),-(0.480035)))))/(1.+(-0.00310177*TMath::Power(1.+((x/0.993569)*(x/0.993569)),-(0.480035))))",
        "333_pt": "(x*0.162735*TMath::Power(TMath::Exp(-0.455874*x-TMath::Abs(-0.0589095)*x*x)+x/1.30284,-5.7907))",
        "443_pt": "x*3.72142e-05/TMath::Power((1+TMath::Power(x/4.06472,2.0)),3.03429)",
        "321_pt": "1.2778632*x*7.70776*TMath::Power(TMath::Exp(-0.618249*x-TMath::Abs(3.16962e-09)*x*x)+x/1.02821,-5.47764)",
        "2212_pt": "1.2778632*x*1.4891*TMath::Power(TMath::Exp(-0.4799*x-TMath::Abs(0.0225614)*x*x)+x/1.6315,-6.82731)"
    },
    "13TeV_MB_16_jpsiup": {
        "histoMtScaleFactor": {
            "113": 0.87,
            "223": 0.572,
            "331": 0.4
        },
        "111_pt": "( x*(55.4505*TMath::Exp(-(TMath::Sqrt(x*x+0.134977*0.134977)-0.134977)/0.14849)+2.93224*TMath::Power(1+(x*x)/(0.64965*0.64965*2.97448),-2.97448)) )",
        "221_pt": "( x*(55.4505*TMath::Exp(-(TMath::Sqrt(x*x+0.134977*0.134977)-0.134977)/0.14849)+2.93224*TMath::Power(1+(x*x)/(0.64965*0.64965*2.97448),-2.97448)) ) * ((0.554328*1.)+(176.93*(-0.00310177*TMath::Power(1.+((x/0.993569)*(x/0.993569)),-(0.480035)))))/(1.+(-0.00310177*TMath::Power(1.+((x/0.993569)*(x/0.993569)),-(0.480035))))",
        "333_pt": "(x*0.162735*TMath::Power(TMath::Exp(-0.455874*x-TMath::Abs(-0.0589095)*x*x)+x/1.30284,-5.7907))",
        "443_pt": "x*4.13769e-05/TMath::Power((1+TMath::Power(x/4.01254,2.0)),3.00288)",
        "321_pt": "1.2778632*x*7.70776*TMath::Power(TMath::Exp(-0.618249*x-TMath::Abs(3.16962e-09)*x*x)+x/1.02821,-5.47764)",
        "2212_pt": "1.2778632*x*1.4891*TMath::Power(TMath::Exp(-0.4799*x-TMath::Abs(0.0225614)*x*x)+x/1.6315,-6.82731)"
    },
    "13TeV_MB_16_jpsidown": {
        "histoMtScaleFactor": {
            "113": 0.87,
            "223": 0.572,
            "331": 0.4
        },
        "111_pt": "( x*(55.4505*TMath::Exp(-(TMath::Sqrt(x*x+0.134977*0.134977)-0.134977)/0.14849)+2.93224*TMath::Power(1+(x*x)/(0.64965*0.64965*2.97448),-2.97448)) )",
        "221_pt": "( x*(55.4505*TMath::Exp(-(TMath::Sqrt(x*x+0.134977*0.134977)-0.134977)/0.14849)+2.93224*TMath::Power(1+(x*x)/(0.64965*0.64965*2.97448),-2.97448)) ) * ((0.554328*1.)+(176.93*(-0.00310177*TMath::Power(1.+((x/0.993569)*(x/0.993569)),-(0.480035)))))/(1.+(-0.00310177*TMath::Power(1.+((x/0.993569)*(x/0.993569)),-(0.480035))))",
        "333_pt": "(x*0.162735*TMath::Power(TMath::Exp(-0.455874*x-TMath::Abs(-0.0589095)*x*x)+x/1.30284,-5.7907))",
        "443_pt": "x*3.30686e-05/TMath::Power((1+TMath::Power(x/4.12933,2.0)),3.07406)",
        "321_pt": "1.2778632*x*7.70776*TMath::Power(TMath::Exp(-0.618249*x-TMath::Abs(3.16962e-09)*x*x)+x/1.02821,-5.47764)",
        "2212_pt": "1.2778632*x*1.4891*TMath::Power(TMath::Exp(-0.4799*x-TMath::Abs(0.0225614)*x*x)+x/1.6315,-6.82731)"
    },
    "13TeV_MB_17_jpsidefault": {
        "histoMtScaleFactor": {
            "113": 0.87,
            "223": 0.572,
            "331": 0.4
        },
        "111_pt": "( x*(55.4505*TMath::Exp(-(TMath::Sqrt(x*x+0.134977*0.134977)-0.134977)/0.14849)+2.93224*TMath::Power(1+(x*x)/(0.64965*0.64965*2.97448),-2.97448)) )",
        "221_pt": "( x*(55.4505*TMath::Exp(-(TMath::Sqrt(x*x+0.134977*0.134977)-0.134977)/0.14849)+2.93224*TMath::Power(1+(x*x)/(0.64965*0.64965*2.97448),-2.97448)) ) * ((0.554328*1.)+(176.93*(-0.00310177*TMath::Power(1.+((x/0.993569)*(x/0.993569)),-(0.480035)))))/(1.+(-0.00310177*TMath::Power(1.+((x/0.993569)*(x/0.993569)),-(0.480035))))",
        "333_pt": "(x*0.162735*TMath::Power(TMath::Exp(-0.455874*x-TMath::Abs(-0.0589095)*x*x)+x/1.30284,-5.7907))",
        "443_pt": "x*3.74318e-05/TMath::Power((1+TMath::Power(x/4.0647,2.0)),3.03428)",
        "321_pt": "1.2778632*x*7.70776*TMath::Power(TMath::Exp(-0.618249*x-TMath::Abs(3.16962e-09)*x*x)+x/1.02821,-5.47764)",
        "2212_pt": "1.2778632*x*1.4891*TMath::Power(TMath::Exp(-0.4799*x-TMath::Abs(0.0225614)*x*x)+x/1.6315,-6.82731)"
    },
    "13TeV_MB_17_jpsiup": {
        "histoMtScaleFactor": {
            "113": 0.87,
            "223": 0.572,
            "331": 0.4
        },
        "111_pt": "( x*(55.4505*TMath::Exp(-(TMath::Sqrt(x*x+0.134977*0.134977)-0.134977)/0.14849)+2.93224*TMath::Power(1+(x*x)/(0.64965*0.64965*2.97448),-2.97448)) )",
        "221_pt": "( x*(55.4505*TMath::Exp(-(TMath::Sqrt(x*x+0.134977*0.134977)-0.134977)/0.14849)+2.93224*TMath::Power(1+(x*x)/(0.64965*0.64965*2.97448),-2.97448)) ) * ((0.554328*1.)+(176.93*(-0.00310177*TMath::Power(1.+((x/0.993569)*(x/0.993569)),-(0.480035)))))/(1.+(-0.00310177*TMath::Power(1.+((x/0.993569)*(x/0.993569)),-(0.480035))))",
        "333_pt": "(x*0.162735*TMath::Power(TMath::Exp(-0.455874*x-TMath::Abs(-0.0589095)*x*x)+x/1.30284,-5.7907))",
        "443_pt": "x*4.16191e-05/TMath::Power((1+TMath::Power(x/4.01253,2.0)),3.00288)",
        "321_pt": "1.2778632*x*7.70776*TMath::Power(TMath::Exp(-0.618249*x-TMath::Abs(3.16962e-09)*x*x)+x/1.02821,-5.47764)",
        "2212_pt": "1.2778632*x*1.4891*TMath::Power(TMath::Exp(-0.4799*x-TMath::Abs(0.0225614)*x*x)+x/1.6315,-6.82731)"
    },
    "13TeV_MB_17_jpsidown": {
        "histoMtScaleFactor": {
            "113": 0.87,
            "223": 0.572,
            "331": 0.4
        },
        "111_pt": "( x*(55.4505*TMath::Exp(-(TMath::Sqrt(x*x+0.134977*0.134977)-0.134977)/0.14849)+2.93224*TMath::Power(1+(x*x)/(0.64965*0.64965*2.97448),-2.97448)) )",
        "221_pt": "( x*(55.4505*TMath::Exp(-(TMath::Sqrt(x*x+0.134977*0.134977)-0.134977)/0.14849)+2.93224*TMath::Power(1+(x*x)/(0.64965*0.64965*2.97448),-2.97448)) ) * ((0.554328*1.)+(176.93*(-0.00310177*TMath::Power(1.+((x/0.993569)*(x/0.993569)),-(0.480035)))))/(1.+(-0.00310177*TMath::Power(1.+((x/0.993569)*(x/0.993569)),-(0.480035))))",
        "333_pt": "(x*0.162735*TMath::Power(TMath::Exp(-0.455874*x-TMath::Abs(-0.0589095)*x*x)+x/1.30284,-5.7907))",
        "443_pt": "x*3.32621e-05/TMath::Power((1+TMath::Power(x/4.12933,2.0)),3.07406)",
        "321_pt": "1.2778632*x*7.70776*TMath::Power(TMath::Exp(-0.618249*x-TMath::Abs(3.16962e-09)*x*x)+x/1.02821,-5.47764)",
        "2212_pt": "1.2778632*x*1.4891*TMath::Power(TMath::Exp(-0.4799*x-TMath::Abs(0.0225614)*x*x)+x/1.6315,-6.82731)"
    },
    "13TeV_MB_Prelim_default": {
        "histoMtScaleFactor": {
            "113": 0.87,
            "223": 0.572,
            "331": 0.4
        },
        "111_pt": "( x*(75.2389*TMath::Exp(-(TMath::Sqrt(x*x+0.134977*0.134977)-0.134977)/0.147008)+2.927*TMath::Power(1+(x*x)/(0.655054*0.655054*2.96614),-2.96614)) )",
        "221_pt": "( x*(75.2389*TMath::Exp(-(TMath::Sqrt(x*x+0.134977*0.134977)-0.134977)/0.147008)+2.927*TMath::Power(1+(x*x)/(0.655054*0.655054*2.96614),-2.96614)) ) * ( ((0.554112*1.)+(158.594*(-0.00305691*TMath::Power(1.+((x/1.52352)*(x/1.52352)),-(0.656663)))))/(1.+(-0.00305691*TMath::Power(1.+((x/1.52352)*(x/1.52352)),-(0.656663)))) )",
        "333_pt": "(x*0.162735*TMath::Power(TMath::Exp(-0.455874*x-TMath::Abs(-0.0589095)*x*x)+x/1.30284,-5.7907))",
        "443_pt": "x*3.76783e-05/TMath::Power((1+TMath::Power(x/4.06472,2.0)),3.03429)",
        "321_pt": "1.2778632*x*7.70776*TMath::Power(TMath::Exp(-0.618249*x-TMath::Abs(3.16962e-09)*x*x)+x/1.02821,-5.47764)",
        "2212_pt": "1.2778632*x*1.4891*TMath::Power(TMath::Exp(-0.4799*x-TMath::Abs(0.0225614)*x*x)+x/1.6315,-6.82731)"
    },
    "13TeV_MB_Prelim_etaup": {
        "histoMtScaleFactor": {
            "113": 0.87,
            "223": 0.572,
            "331": 0.4
        },
        "111_pt": "( x*(75.2389*TMath::Exp(-(TMath::Sqrt(x*x+0.134977*0.134977)-0.134977)/0.147008)+2.927*TMath::Power(1+(x*x)/(0.655054*0.655054*2.96614),-2.96614)) )",
        "221_pt": "( x*(75.2389*TMath::Exp(-(TMath::Sqrt(x*x+0.134977*0.134977)-0.134977)/0.147008)+2.927*TMath::Power(1+(x*x)/(0.655054*0.655054*2.96614),-2.96614)) ) * ( ((0.61306*1.)+(167.497*(-0.00322916*TMath::Power(1.+((x/1.29507)*(x/1.29507)),-(0.491599)))))/(1.+(-0.00322916*TMath::Power(1.+((x/1.29507)*(x/1.29507)),-(0.491599)))) )",
        "333_pt": "(x*0.162735*TMath::Power(TMath::Exp(-0.455874*x-TMath::Abs(-0.0589095)*x*x)+x/1.30284,-5.7907))",
        "443_pt": "x*3.76783e-05/TMath::Power((1+TMath::Power(x/4.06472,2.0)),3.03429)",
        "321_pt": "1.2778632*x*7.70776*TMath::Power(TMath::Exp(-0.618249*x-TMath::Abs(3.16962e-09)*x*x)+x/1.02821,-5.47764)",
        "2212_pt": "1.2778632*x*1.4891*TMath::Power(TMath::Exp(-0.4799*x-TMath::Abs(0.0225614)*x*x)+x/1.6315,-6.82731)"
    },
    "13TeV_MB_Prelim_etadown": {
        "histoMtScaleFactor": {
            "113": 0.87,
            "223": 0.572,
            "331": 0.4
        },
        "111_pt": "( x*(75.2389*TMath::Exp(-(TMath::Sqrt(x*x+0.134977*0.134977)-0.134977)/0.147008)+2.927*TMath::Power(1+(x*x)/(0.655054*0.655054*2.96614),-2.96614)) )",
        "221_pt": "( x*(75.2389*TMath::Exp(-(TMath::Sqrt(x*x+0.134977*0.134977)-0.134977)/0.147008)+2.927*TMath::Power(1+(x*x)/(0.655054*0.655054*2.96614),-2.96614)) ) * ( ((0.507127*1.)+(151.313*(-0.00291596*TMath::Power(1.+((x/1.81365)*(x/1.81365)),-(0.888791)))))/(1.+(-0.00291596*TMath::Power(1.+((x/1.81365)*(x/1.81365)),-(0.888791)))) )",
        "333_pt": "(x*0.162735*TMath::Power(TMath::Exp(-0.455874*x-TMath::Abs(-0.0589095)*x*x)+x/1.30284,-5.7907))",
        "443_pt": "x*3.76783e-05/TMath::Power((1+TMath::Power(x/4.06472,2.0)),3.03429)",
        "321_pt": "1.2778632*x*7.70776*TMath::Power(TMath::Exp(-0.618249*x-TMath::Abs(3.16962e-09)*x*x)+x/1.02821,-5.47764)",
        "2212_pt": "1.2778632*x*1.4891*TMath::Power(TMath::Exp(-0.4799*x-TMath::Abs(0.0225614)*x*x)+x/1.6315,-6.82731)"
    },
    "13TeV_MB_Prelim_pi0up_eta": {
        "histoMtScaleFactor": {
            "113": 0.87,
            "223": 0.572,
            "331": 0.4
        },
        "111_pt": "( x*(75.2389*TMath::Exp(-(TMath::Sqrt(x*x+0.134977*0.134977)-0.134977)/0.147008)+2.927*TMath::Power(1+(x*x)/(0.655054*0.655054*2.96614),-2.96614)) )",
        "221_pt": "( x*(104.34*TMath::Exp(-(TMath::Sqrt(x*x+0.134977*0.134977)-0.134977)/0.135354)+3.60886*TMath::Power(1+(x*x)/(0.62862*0.62862*2.9374),-2.9374)) ) * ( ((0.554112*1.)+(158.594*(-0.00305691*TMath::Power(1.+((x/1.52352)*(x/1.52352)),-(0.656663)))))/(1.+(-0.00305691*TMath::Power(1.+((x/1.52352)*(x/1.52352)),-(0.656663)))) )",
        "333_pt": "(x*0.162735*TMath::Power(TMath::Exp(-0.455874*x-TMath::Abs(-0.0589095)*x*x)+x/1.30284,-5.7907))",
        "443_pt": "x*3.76783e-05/TMath::Power((1+TMath::Power(x/4.06472,2.0)),3.03429)",
        "321_pt": "1.2778632*x*7.70776*TMath::Power(TMath::Exp(-0.618249*x-TMath::Abs(3.16962e-09)*x*x)+x/1.02821,-5.47764)",
        "2212_pt": "1.2778632*x*1.4891*TMath::Power(TMath::Exp(-0.4799*x-TMath::Abs(0.0225614)*x*x)+x/1.6315,-6.82731)"
    },
    "13TeV_MB_Prelim_pi0up_etaup": {
        "histoMtScaleFactor": {
            "113": 0.87,
            "223": 0.572,
            "331": 0.4
        },
        "111_pt": "( x*(75.2389*TMath::Exp(-(TMath::Sqrt(x*x+0.134977*0.134977)-0.134977)/0.147008)+2.927*TMath::Power(1+(x*x)/(0.655054*0.655054*2.96614),-2.96614)) )",
        "221_pt": "( x*(104.34*TMath::Exp(-(TMath::Sqrt(x*x+0.134977*0.134977)-0.134977)/0.135354)+3.60886*TMath::Power(1+(x*x)/(0.62862*0.62862*2.9374),-2.9374)) ) * ( ((0.61306*1.)+(167.497*(-0.00322916*TMath::Power(1.+((x/1.29507)*(x/1.29507)),-(0.491599)))))/(1.+(-0.00322916*TMath::Power(1.+((x/1.29507)*(x/1.29507)),-(0.491599)))) )",
        "333_pt": "(x*0.162735*TMath::Power(TMath::Exp(-0.455874*x-TMath::Abs(-0.0589095)*x*x)+x/1.30284,-5.7907))",
        "443_pt": "x*3.76783e-05/TMath::Power((1+TMath::Power(x/4.06472,2.0)),3.03429)",
        "321_pt": "1.2778632*x*7.70776*TMath::Power(TMath::Exp(-0.618249*x-TMath::Abs(3.16962e-09)*x*x)+x/1.02821,-5.47764)",
        "2212_pt": "1.2778632*x*1.4891*TMath::Power(TMath::Exp(-0.4799*x-TMath::Abs(0.0225614)*x*x)+x/1.6315,-6.82731)"
    },
    "13TeV_MB_Prelim_pi0up_etadown": {
        "histoMtScaleFactor": {
            "113": 0.87,
            "223": 0.572,
            "331": 0.4
        },
        "111_pt": "( x*(75.2389*TMath::Exp(-(TMath::Sqrt(x*x+0.134977*0.134977)-0.134977)/0.147008)+2.927*TMath::Power(1+(x*x)/(0.655054*0.655054*2.96614),-2.96614)) )",
        "221_pt": "( x*(104.34*TMath::Exp(-(TMath::Sqrt(x*x+0.134977*0.134977)-0.134977)/0.135354)+3.60886*TMath::Power(1+(x*x)/(0.62862*0.62862*2.9374),-2.9374)) ) * ( ((0.507127*1.)+(151.313*(-0.00291596*TMath::Power(1.+((x/1.81365)*(x/1.81365)),-(0.888791)))))/(1.+(-0.00291596*TMath::Power(1.+((x/1.81365)*(x/1.81365)),-(0.888791)))) )",
        "333_pt": "(x*0.162735*TMath::Power(TMath::Exp(-0.455874*x-TMath::Abs(-0.0589095)*x*x)+x/1.30284,-5.7907))",
        "443_pt": "x*3.76783e-05/TMath::Power((1+TMath::Power(x/4.06472,2.0)),3.03429)",
        "321_pt": "1.2778632*x*7.70776*TMath::Power(TMath::Exp(-0.618249*x-TMath::Abs(3.16962e-09)*x*x)+x/1.02821,-5.47764)",
        "2212_pt": "1.2778632*x*1.4891*TMath::Power(TMath::Exp(-0.4799*x-TMath::Abs(0.0225614)*x*x)+x/1.6315,-6.82731)"
    },
    "13TeV_MB_Prelim_pi0down_eta": {
        "histoMtScaleFactor": {
            "113": 0.87,
            "223": 0.572,
            "331": 0.4
        },
        "111_pt": "( x*(75.2389*TMath::Exp(-(TMath::Sqrt(x*x+0.134977*0.134977)-0.134977)/0.147008)+2.927*TMath::Power(1+(x*x)/(0.655054*0.655054*2.96614),-2.96614)) )",
        "221_pt": "( x*(52.8954*TMath::Exp(-(TMath::Sqrt(x*x+0.134977*0.134977)-0.134977)/0.162106)+2.25247*TMath::Power(1+(x*x)/(0.690119*0.690119*3.00143),-3.00143)) ) * ( ((0.554112*1.)+(158.594*(-0.00305691*TMath::Power(1.+((x/1.52352)*(x/1.52352)),-(0.656663)))))/(1.+(-0.00305691*TMath::Power(1.+((x/1.52352)*(x/1.52352)),-(0.656663)))) )",
        "333_pt": "(x*0.162735*TMath::Power(TMath::Exp(-0.455874*x-TMath::Abs(-0.0589095)*x*x)+x/1.30284,-5.7907))",
        "443_pt": "x*3.76783e-05/TMath::Power((1+TMath::Power(x/4.06472,2.0)),3.03429)",
        "321_pt": "1.2778632*x*7.70776*TMath::Power(TMath::Exp(-0.618249*x-TMath::Abs(3.16962e-09)*x*x)+x/1.02821,-5.47764)",
        "2212_pt": "1.2778632*x*1.4891*TMath::Power(TMath::Exp(-0.4799*x-TMath::Abs(0.0225614)*x*x)+x/1.6315,-6.82731)"
    },
    "13TeV_MB_Prelim_pi0down_etaup": {
        "histoMtScaleFactor": {
            "113": 0.87,
            "223": 0.572,
            "331": 0.4
        },
        "111_pt": "( x*(75.2389*TMath::Exp(-(TMath::Sqrt(x*x+0.134977*0.134977)-0.134977)/0.147008)+2.927*TMath::Power(1+(x*x)/(0.655054*0.655054*2.96614),-2.96614)) )",
        "221_pt": "( x*(52.8954*TMath::Exp(-(TMath::Sqrt(x*x+0.134977*0.134977)-0.134977)/0.162106)+2.25247*TMath::Power(1+(x*x)/(0.690119*0.690119*3.00143),-3.00143)) ) * ( ((0.61306*1.)+(167.497*(-0.00322916*TMath::Power(1.+((x/1.29507)*(x/1.29507)),-(0.491599)))))/(1.+(-0.00322916*TMath::Power(1.+((x/1.29507)*(x/1.29507)),-(0.491599)))) )",
        "333_pt": "(x*0.162735*TMath::Power(TMath::Exp(-0.455874*x-TMath::Abs(-0.0589095)*x*x)+x/1.30284,-5.7907))",
        "443_pt": "x*3.76783e-05/TMath::Power((1+TMath::Power(x/4.06472,2.0)),3.03429)",
        "321_pt": "1.2778632*x*7.70776*TMath::Power(TMath::Exp(-0.618249*x-TMath::Abs(3.16962e-09)*x*x)+x/1.02821,-5.47764)",
        "2212_pt": "1.2778632*x*1.4891*TMath::Power(TMath::Exp(-0.4799*x-TMath::Abs(0.0225614)*x*x)+x/1.6315,-6.82731)"
    },
    "13TeV_MB_Prelim_pi0down_etadown": {
        "histoMtScaleFactor": {
            "113": 0.87,
            "223": 0.572,
            "331": 0.4
        },
        "111_pt": "( x*(75.2389*TMath::Exp(-(TMath::Sqrt(x*x+0.134977*0.134977)-0.134977)/0.147008)+2.927*TMath::Power(1+(x*x)/(0.655054*0.655054*2.96614),-2.96614)) )",
        "221_pt": "( x*(52.8954*TMath::Exp(-(TMath::Sqrt(x*x+0.134977*0.134977)-0.134977)/0.162106)+2.25247*TMath::Power(1+(x*x)/(0.690119*0.690119*3.00143),-3.00143)) ) * ( ((0.507127*1.)+(151.313*(-0.00291596*TMath::Power(1.+((x/1.81365)*(x/1.81365)),-(0.888791)))))/(1.+(-0.00291596*TMath::Power(1.+((x/1.81365)*(x/1.81365)),-(0.888791)))) )",
        "333_pt": "(x*0.162735*TMath::Power(TMath::Exp(-0.455874*x-TMath::Abs(-0.0589095)*x*x)+x/1.30284,-5.7907))",
        "443_pt": "x*3.76783e-05/TMath::Power((1+TMath::Power(x/4.06472,2.0)),3.03429)",
        "321_pt": "1.2778632*x*7.70776*TMath::Power(TMath::Exp(-0.618249*x-TMath::Abs(3.16962e-09)*x*x)+x/1.02821,-5.47764)",
        "2212_pt": "1.2778632*x*1.4891*TMath::Power(TMath::Exp(-0.4799*x-TMath::Abs(0.0225614)*x*x)+x/1.6315,-6.82731)"
    },
    "13TeV_HM_default": {
        "histoMtScaleFactor": {
            "113": 0.87,
            "223": 0.572,
            "331": 0.4
        },
        "111_pt": "( x*(326.754*TMath::Exp(-(TMath::Sqrt(x*x+0.134977*0.134977)-0.134977)/0.140039)+17.4259*TMath::Power(1+(x*x)/(0.685364*0.685364*2.88243),-2.88243)) )",
        "221_pt": "( x*(326.754*TMath::Exp(-(TMath::Sqrt(x*x+0.134977*0.134977)-0.134977)/0.140039)+17.4259*TMath::Power(1+(x*x)/(0.685364*0.685364*2.88243),-2.88243)) ) *   ((0.691819*1.)+(180.263*(-0.00350264*TMath::Power(1.+((x/0.91991)*(x/0.91991)),-(0.242107)))))/(1.+(-0.00350264*TMath::Power(1.+((x/0.91991)*(x/0.91991)),-(0.242107))))",
        "333_pt": "(1.217*x*0.44822*TMath::Power(TMath::Exp(-0.364259*x-TMath::Abs(-0.12213)*x*x)+x/1.42716,-5.37383))",
        "443_pt": "x*3.76783e-05/TMath::Power((1+TMath::Power(x/4.06472,2.0)),3.03429)",
        "321_pt": "1.2778632*x*7.70776*TMath::Power(TMath::Exp(-0.618249*x-TMath::Abs(3.16962e-09)*x*x)+x/1.02821,-5.47764)",
        "2212_pt": "1.2778632*x*1.4891*TMath::Power(TMath::Exp(-0.4799*x-TMath::Abs(0.0225614)*x*x)+x/1.6315,-6.82731)"
    },
    "13TeV_HM_etaup": {
        "histoMtScaleFactor": {
            "113": 0.87,
            "223": 0.572,
            "331": 0.4
        },
        "111_pt": "( x*(326.754*TMath::Exp(-(TMath::Sqrt(x*x+0.134977*0.134977)-0.134977)/0.140039)+17.4259*TMath::Power(1+(x*x)/(0.685364*0.685364*2.88243),-2.88243)) )",
        "221_pt": "( x*(326.754*TMath::Exp(-(TMath::Sqrt(x*x+0.134977*0.134977)-0.134977)/0.140039)+17.4259*TMath::Power(1+(x*x)/(0.685364*0.685364*2.88243),-2.88243)) ) *   ((0.799845*1.)+(192.141*(-0.00373188*TMath::Power(1.+((x/0.953155)*(x/0.953155)),-(0.199252)))))/(1.+(-0.00373188*TMath::Power(1.+((x/0.953155)*(x/0.953155)),-(0.199252))))",
        "333_pt": "(1.217*x*0.44822*TMath::Power(TMath::Exp(-0.364259*x-TMath::Abs(-0.12213)*x*x)+x/1.42716,-5.37383))",
        "443_pt": "x*3.76783e-05/TMath::Power((1+TMath::Power(x/4.06472,2.0)),3.03429)",
        "321_pt": "1.2778632*x*7.70776*TMath::Power(TMath::Exp(-0.618249*x-TMath::Abs(3.16962e-09)*x*x)+x/1.02821,-5.47764)",
        "2212_pt": "1.2778632*x*1.4891*TMath::Power(TMath::Exp(-0.4799*x-TMath::Abs(0.0225614)*x*x)+x/1.6315,-6.82731)"
    },
    "13TeV_HM_etadown": {
        "histoMtScaleFactor": {
            "113": 0.87,
            "223": 0.572,
            "331": 0.4
        },
        "111_pt": "( x*(326.754*TMath::Exp(-(TMath::Sqrt(x*x+0.134977*0.134977)-0.134977)/0.140039)+17.4259*TMath::Power(1+(x*x)/(0.685364*0.685364*2.88243),-2.88243)) )",
        "221_pt": "( x*(326.754*TMath::Exp(-(TMath::Sqrt(x*x+0.134977*0.134977)-0.134977)/0.140039)+17.4259*TMath::Power(1+(x*x)/(0.685364*0.685364*2.88243),-2.88243)) ) *   ((0.60826*1.)+(171.512*(-0.00333377*TMath::Power(1.+((x/0.891623)*(x/0.891623)),-(0.289837)))))/(1.+(-0.00333377*TMath::Power(1.+((x/0.891623)*(x/0.891623)),-(0.289837))))",
        "333_pt": "(1.217*x*0.44822*TMath::Power(TMath::Exp(-0.364259*x-TMath::Abs(-0.12213)*x*x)+x/1.42716,-5.37383))",
        "443_pt": "x*3.76783e-05/TMath::Power((1+TMath::Power(x/4.06472,2.0)),3.03429)",
        "321_pt": "1.2778632*x*7.70776*TMath::Power(TMath::Exp(-0.618249*x-TMath::Abs(3.16962e-09)*x*x)+x/1.02821,-5.47764)",
        "2212_pt": "1.2778632*x*1.4891*TMath::Power(TMath::Exp(-0.4799*x-TMath::Abs(0.0225614)*x*x)+x/1.6315,-6.82731)"
    },
    "13TeV_HM_pi0up_eta": {
        "histoMtScaleFactor": {
            "113": 0.87,
            "223": 0.572,
            "331": 0.4
        },
        "111_pt": "( x*(326.754*TMath::Exp(-(TMath::Sqrt(x*x+0.134977*0.134977)-0.134977)/0.140039)+17.4259*TMath::Power(1+(x*x)/(0.685364*0.685364*2.88243),-2.88243)) )",
        "221_pt": "( x*(497.744*TMath::Exp(-(TMath::Sqrt(x*x+0.134977*0.134977)-0.134977)/0.128497)+19.8436*TMath::Power(1+(x*x)/(0.669985*0.669985*2.86007),-2.86007)) ) *   ((0.691819*1.)+(180.263*(-0.00350264*TMath::Power(1.+((x/0.91991)*(x/0.91991)),-(0.242107)))))/(1.+(-0.00350264*TMath::Power(1.+((x/0.91991)*(x/0.91991)),-(0.242107))))",
        "333_pt": "(1.217*x*0.44822*TMath::Power(TMath::Exp(-0.364259*x-TMath::Abs(-0.12213)*x*x)+x/1.42716,-5.37383))",
        "443_pt": "x*3.76783e-05/TMath::Power((1+TMath::Power(x/4.06472,2.0)),3.03429)",
        "321_pt": "1.2778632*x*7.70776*TMath::Power(TMath::Exp(-0.618249*x-TMath::Abs(3.16962e-09)*x*x)+x/1.02821,-5.47764)",
        "2212_pt": "1.2778632*x*1.4891*TMath::Power(TMath::Exp(-0.4799*x-TMath::Abs(0.0225614)*x*x)+x/1.6315,-6.82731)"
    },
    "13TeV_HM_pi0up_etaup": {
        "histoMtScaleFactor": {
            "113": 0.87,
            "223": 0.572,
            "331": 0.4
        },
        "111_pt": "( x*(326.754*TMath::Exp(-(TMath::Sqrt(x*x+0.134977*0.134977)-0.134977)/0.140039)+17.4259*TMath::Power(1+(x*x)/(0.685364*0.685364*2.88243),-2.88243)) )",
        "221_pt": "( x*(497.744*TMath::Exp(-(TMath::Sqrt(x*x+0.134977*0.134977)-0.134977)/0.128497)+19.8436*TMath::Power(1+(x*x)/(0.669985*0.669985*2.86007),-2.86007)) ) *   ((0.799845*1.)+(192.141*(-0.00373188*TMath::Power(1.+((x/0.953155)*(x/0.953155)),-(0.199252)))))/(1.+(-0.00373188*TMath::Power(1.+((x/0.953155)*(x/0.953155)),-(0.199252))))",
        "333_pt": "(1.217*x*0.44822*TMath::Power(TMath::Exp(-0.364259*x-TMath::Abs(-0.12213)*x*x)+x/1.42716,-5.37383))",
        "443_pt": "x*3.76783e-05/TMath::Power((1+TMath::Power(x/4.06472,2.0)),3.03429)",
        "321_pt": "1.2778632*x*7.70776*TMath::Power(TMath::Exp(-0.618249*x-TMath::Abs(3.16962e-09)*x*x)+x/1.02821,-5.47764)",
        "2212_pt": "1.2778632*x*1.4891*TMath::Power(TMath::Exp(-0.4799*x-TMath::Abs(0.0225614)*x*x)+x/1.6315,-6.82731)"
    },
    "13TeV_HM_pi0up_etadown": {
        "histoMtScaleFactor": {
            "113": 0.87,
            "223": 0.572,
            "331": 0.4
        },
        "111_pt": "( x*(326.754*TMath::Exp(-(TMath::Sqrt(x*x+0.134977*0.134977)-0.134977)/0.140039)+17.4259*TMath::Power(1+(x*x)/(0.685364*0.685364*2.88243),-2.88243)) )",
        "221_pt": "( x*(497.744*TMath::Exp(-(TMath::Sqrt(x*x+0.134977*0.134977)-0.134977)/0.128497)+19.8436*TMath::Power(1+(x*x)/(0.669985*0.669985*2.86007),-2.86007)) ) *   ((0.60826*1.)+(171.512*(-0.00333377*TMath::Power(1.+((x/0.891623)*(x/0.891623)),-(0.289837)))))/(1.+(-0.00333377*TMath::Power(1.+((x/0.891623)*(x/0.891623)),-(0.289837))))",
        "333_pt": "(1.217*x*0.44822*TMath::Power(TMath::Exp(-0.364259*x-TMath::Abs(-0.12213)*x*x)+x/1.42716,-5.37383))",
        "443_pt": "x*3.76783e-05/TMath::Power((1+TMath::Power(x/4.06472,2.0)),3.03429)",
        "321_pt": "1.2778632*x*7.70776*TMath::Power(TMath::Exp(-0.618249*x-TMath::Abs(3.16962e-09)*x*x)+x/1.02821,-5.47764)",
        "2212_pt": "1.2778632*x*1.4891*TMath::Power(TMath::Exp(-0.4799*x-TMath::Abs(0.0225614)*x*x)+x/1.6315,-6.82731)"
    },
    "13TeV_HM_pi0down_eta": {
        "histoMtScaleFactor": {
            "113": 0.87,
            "223": 0.572,
            "331": 0.4
        },
        "111_pt": "( x*(326.754*TMath::Exp(-(TMath::Sqrt(x*x+0.134977*0.134977)-0.134977)/0.140039)+17.4259*TMath::Power(1+(x*x)/(0.685364*0.685364*2.88243),-2.88243)) )",
        "221_pt": "( x*(204.529*TMath::Exp(-(TMath::Sqrt(x*x+0.134977*0.134977)-0.134977)/0.155686)+14.9262*TMath::Power(1+(x*x)/(0.704871*0.704871*2.90918),-2.90918)) ) *   ((0.691819*1.)+(180.263*(-0.00350264*TMath::Power(1.+((x/0.91991)*(x/0.91991)),-(0.242107)))))/(1.+(-0.00350264*TMath::Power(1.+((x/0.91991)*(x/0.91991)),-(0.242107))))",
        "333_pt": "(1.217*x*0.44822*TMath::Power(TMath::Exp(-0.364259*x-TMath::Abs(-0.12213)*x*x)+x/1.42716,-5.37383))",
        "443_pt": "x*3.76783e-05/TMath::Power((1+TMath::Power(x/4.06472,2.0)),3.03429)",
        "321_pt": "1.2778632*x*7.70776*TMath::Power(TMath::Exp(-0.618249*x-TMath::Abs(3.16962e-09)*x*x)+x/1.02821,-5.47764)",
        "2212_pt": "1.2778632*x*1.4891*TMath::Power(TMath::Exp(-0.4799*x-TMath::Abs(0.0225614)*x*x)+x/1.6315,-6.82731)"
    },
    "13TeV_HM_pi0down_etaup": {
        "histoMtScaleFactor": {
            "113": 0.87,
            "223": 0.572,
            "331": 0.4
        },
        "111_pt": "( x*(326.754*TMath::Exp(-(TMath::Sqrt(x*x+0.134977*0.134977)-0.134977)/0.140039)+17.4259*TMath::Power(1+(x*x)/(0.685364*0.685364*2.88243),-2.88243)) )",
        "221_pt": "( x*(204.529*TMath::Exp(-(TMath::Sqrt(x*x+0.134977*0.134977)-0.134977)/0.155686)+14.9262*TMath::Power(1+(x*x)/(0.704871*0.704871*2.90918),-2.90918)) ) *   ((0.799845*1.)+(192.141*(-0.00373188*TMath::Power(1.+((x/0.953155)*(x/0.953155)),-(0.199252)))))/(1.+(-0.00373188*TMath::Power(1.+((x/0.953155)*(x/0.953155)),-(0.199252))))",
        "333_pt": "(1.217*x*0.44822*TMath::Power(TMath::Exp(-0.364259*x-TMath::Abs(-0.12213)*x*x)+x/1.42716,-5.37383))",
        "443_pt": "x*3.76783e-05/TMath::Power((1+TMath::Power(x/4.06472,2.0)),3.03429)",
        "321_pt": "1.2778632*x*7.70776*TMath::Power(TMath::Exp(-0.618249*x-TMath::Abs(3.16962e-09)*x*x)+x/1.02821,-5.47764)",
        "2212_pt": "1.2778632*x*1.4891*TMath::Power(TMath::Exp(-0.4799*x-TMath::Abs(0.0225614)*x*x)+x/1.6315,-6.82731)"
    },
    "13TeV_HM_pi0down_etadown": {
        "histoMtScaleFactor": {
            "113": 0.87,
            "223": 0.572,
            "331": 0.4
        },
        "111_pt": "( x*(326.754*TMath::Exp(-(TMath::Sqrt(x*x+0.134977*0.134977)-0.134977)/0.140039)+17.4259*TMath::Power(1+(x*x)/(0.685364*0.685364*2.88243),-2.88243)) )",
        "221_pt": "( x*(204.529*TMath::Exp(-(TMath::Sqrt(x*x+0.134977*0.134977)-0.134977)/0.155686)+14.9262*TMath::Power(1+(x*x)/(0.704871*0.704871*2.90918),-2.90918)) ) *   ((0.60826*1.)+(171.512*(-0.00333377*TMath::Power(1.+((x/0.891623)*(x/0.891623)),-(0.289837)))))/(1.+(-0.00333377*TMath::Power(1.+((x/0.891623)*(x/0.891623)),-(0.289837))))",
        "333_pt": "(1.217*x*0.44822*TMath::Power(TMath::Exp(-0.364259*x-TMath::Abs(-0.12213)*x*x)+x/1.42716,-5.37383))",
        "443_pt": "x*3.76783e-05/TMath::Power((1+TMath::Power(x/4.06472,2.0)),3.03429)",
        "321_pt": "1.2778632*x*7.70776*TMath::Power(TMath::Exp(-0.618249*x-TMath::Abs(3.16962e-09)*x*x)+x/1.02821,-5.47764)",
        "2212_pt": "1.2778632*x*1.4891*TMath::Power(TMath::Exp(-0.4799*x-TMath::Abs(0.0225614)*x*x)+x/1.6315,-6.82731)"
    },
    "13TeV_HM_phiup": {
        "histoMtScaleFactor": {
            "113": 0.87,
            "223": 0.572,
            "331": 0.4
        },
        "111_pt": "( x*(326.754*TMath::Exp(-(TMath::Sqrt(x*x+0.134977*0.134977)-0.134977)/0.140039)+17.4259*TMath::Power(1+(x*x)/(0.685364*0.685364*2.88243),-2.88243)) )",
        "221_pt": "( x*(326.754*TMath::Exp(-(TMath::Sqrt(x*x+0.134977*0.134977)-0.134977)/0.140039)+17.4259*TMath::Power(1+(x*x)/(0.685364*0.685364*2.88243),-2.88243)) ) *   ((0.691819*1.)+(180.263*(-0.00350264*TMath::Power(1.+((x/0.91991)*(x/0.91991)),-(0.242107)))))/(1.+(-0.00350264*TMath::Power(1.+((x/0.91991)*(x/0.91991)),-(0.242107))))",
        "333_pt": "1.1*((1.217*x*0.44822*TMath::Power(TMath::Exp(-0.364259*x-TMath::Abs(-0.12213)*x*x)+x/1.42716,-5.37383)))",
        "443_pt": "x*3.76783e-05/TMath::Power((1+TMath::Power(x/4.06472,2.0)),3.03429)",
        "321_pt": "1.2778632*x*7.70776*TMath::Power(TMath::Exp(-0.618249*x-TMath::Abs(3.16962e-09)*x*x)+x/1.02821,-5.47764)",
        "2212_pt": "1.2778632*x*1.4891*TMath::Power(TMath::Exp(-0.4799*x-TMath::Abs(0.0225614)*x*x)+x/1.6315,-6.82731)"
    },
    "13TeV_HM_phidown": {
        "histoMtScaleFactor": {
            "113": 0.87,
            "223": 0.572,
            "331": 0.4
        },
        "111_pt": "( x*(326.754*TMath::Exp(-(TMath::Sqrt(x*x+0.134977*0.134977)-0.134977)/0.140039)+17.4259*TMath::Power(1+(x*x)/(0.685364*0.685364*2.88243),-2.88243)) )",
        "221_pt": "( x*(326.754*TMath::Exp(-(TMath::Sqrt(x*x+0.134977*0.134977)-0.134977)/0.140039)+17.4259*TMath::Power(1+(x*x)/(0.685364*0.685364*2.88243),-2.88243)) ) *   ((0.691819*1.)+(180.263*(-0.00350264*TMath::Power(1.+((x/0.91991)*(x/0.91991)),-(0.242107)))))/(1.+(-0.00350264*TMath::Power(1.+((x/0.91991)*(x/0.91991)),-(0.242107))))",
        "333_pt": "0.9*((1.217*x*0.44822*TMath::Power(TMath::Exp(-0.364259*x-TMath::Abs(-0.12213)*x*x)+x/1.42716,-5.37383)))",
        "443_pt": "x*3.76783e-05/TMath::Power((1+TMath::Power(x/4.06472,2.0)),3.03429)",
        "321_pt": "1.2778632*x*7.70776*TMath::Power(TMath::Exp(-0.618249*x-TMath::Abs(3.16962e-09)*x*x)+x/1.02821,-5.47764)",
        "2212_pt": "1.2778632*x*1.4891*TMath::Power(TMath::Exp(-0.4799*x-TMath::Abs(0.0225614)*x*x)+x/1.6315,-6.82731)"
    },
    "13TeV_HM_phimultup": {
        "histoMtScaleFactor": {
            "113": 0.87,
            "223": 0.572,
            "331": 0.4
        },
        "111_pt": "( x*(326.754*TMath::Exp(-(TMath::Sqrt(x*x+0.134977*0.134977)-0.134977)/0.140039)+17.4259*TMath::Power(1+(x*x)/(0.685364*0.685364*2.88243),-2.88243)) )",
        "221_pt": "( x*(326.754*TMath::Exp(-(TMath::Sqrt(x*x+0.134977*0.134977)-0.134977)/0.140039)+17.4259*TMath::Power(1+(x*x)/(0.685364*0.685364*2.88243),-2.88243)) ) *   ((0.691819*1.)+(180.263*(-0.00350264*TMath::Power(1.+((x/0.91991)*(x/0.91991)),-(0.242107)))))/(1.+(-0.00350264*TMath::Power(1.+((x/0.91991)*(x/0.91991)),-(0.242107))))",
        "333_pt": "(1.2446720*x*0.44822*TMath::Power(TMath::Exp(-0.364259*x-TMath::Abs(-0.12213)*x*x)+x/1.42716,-5.37383))",
        "443_pt": "x*3.76783e-05/TMath::Power((1+TMath::Power(x/4.06472,2.0)),3.03429)",
        "321_pt": "1.2778632*x*7.70776*TMath::Power(TMath::Exp(-0.618249*x-TMath::Abs(3.16962e-09)*x*x)+x/1.02821,-5.47764)",
        "2212_pt": "1.2778632*x*1.4891*TMath::Power(TMath::Exp(-0.4799*x-TMath::Abs(0.0225614)*x*x)+x/1.6315,-6.82731)"
    },
    "13TeV_HM_phimultdown": {
        "histoMtScaleFactor": {
            "113": 0.87,
            "223": 0.572,
            "331": 0.4
        },
        "111_pt": "( x*(326.754*TMath::Exp(-(TMath::Sqrt(x*x+0.134977*0.134977)-0.134977)/0.140039)+17.4259*TMath::Power(1+(x*x)/(0.685364*0.685364*2.88243),-2.88243)) )",
        "221_pt": "( x*(326.754*TMath::Exp(-(TMath::Sqrt(x*x+0.134977*0.134977)-0.134977)/0.140039)+17.4259*TMath::Power(1+(x*x)/(0.685364*0.685364*2.88243),-2.88243)) ) *   ((0.691819*1.)+(180.263*(-0.00350264*TMath::Power(1.+((x/0.91991)*(x/0.91991)),-(0.242107)))))/(1.+(-0.00350264*TMath::Power(1.+((x/0.91991)*(x/0.91991)),-(0.242107))))",
        "333_pt": "(1.1893474*x*0.44822*TMath::Power(TMath::Exp(-0.364259*x-TMath::Abs(-0.12213)*x*x)+x/1.42716,-5.37383))",
        "443_pt": "x*3.76783e-05/TMath::Power((1+TMath::Power(x/4.06472,2.0)),3.03429)",
        "321_pt": "1.2778632*x*7.70776*TMath::Power(TMath::Exp(-0.618249*x-TMath::Abs(3.16962e-09)*x*x)+x/1.02821,-5.47764)",
        "2212_pt": "1.2778632*x*1.4891*TMath::Power(TMath::Exp(-0.4799*x-TMath::Abs(0.0225614)*x*x)+x/1.6315,-6.82731)"
    },
    "13TeV_HM_etapup": {
        "histoMtScaleFactor": {
            "113": 0.87,
            "223": 0.572,
            "331": 0.48
        },
        "111_pt": "( x*(326.754*TMath::Exp(-(TMath::Sqrt(x*x+0.134977*0.134977)-0.134977)/0.140039)+17.4259*TMath::Power(1+(x*x)/(0.685364*0.685364*2.88243),-2.88243)) )",
        "221_pt": "( x*(326.754*TMath::Exp(-(TMath::Sqrt(x*x+0.134977*0.134977)-0.134977)/0.140039)+17.4259*TMath::Power(1+(x*x)/(0.685364*0.685364*2.88243),-2.88243)) ) *   ((0.691819*1.)+(180.263*(-0.00350264*TMath::Power(1.+((x/0.91991)*(x/0.91991)),-(0.242107)))))/(1.+(-0.00350264*TMath::Power(1.+((x/0.91991)*(x/0.91991)),-(0.242107))))",
        "333_pt": "(1.217*x*0.44822*TMath::Power(TMath::Exp(-0.364259*x-TMath::Abs(-0.12213)*x*x)+x/1.42716,-5.37383))",
        "443_pt": "x*3.76783e-05/TMath::Power((1+TMath::Power(x/4.06472,2.0)),3.03429)",
        "321_pt": "1.2778632*x*7.70776*TMath::Power(TMath::Exp(-0.618249*x-TMath::Abs(3.16962e-09)*x*x)+x/1.02821,-5.47764)",
        "2212_pt": "1.2778632*x*1.4891*TMath::Power(TMath::Exp(-0.4799*x-TMath::Abs(0.0225614)*x*x)+x/1.6315,-6.82731)"
    },
    "13TeV_HM_etapdown": {
        "histoMtScaleFactor": {
            "113": 0.87,
            "223": 0.572,
            "331": 0.32
        },
        "111_pt": "( x*(326.754*TMath::Exp(-(TMath::Sqrt(x*x+0.134977*0.134977)-0.134977)/0.140039)+17.4259*TMath::Power(1+(x*x)/(0.685364*0.685364*2.88243),-2.88243)) )",
        "221_pt": "( x*(326.754*TMath::Exp(-(TMath::Sqrt(x*x+0.134977*0.134977)-0.134977)/0.140039)+17.4259*TMath::Power(1+(x*x)/(0.685364*0.685364*2.88243),-2.88243)) ) *   ((0.691819*1.)+(180.263*(-0.00350264*TMath::Power(1.+((x/0.91991)*(x/0.91991)),-(0.242107)))))/(1.+(-0.00350264*TMath::Power(1.+((x/0.91991)*(x/0.91991)),-(0.242107))))",
        "333_pt": "(1.217*x*0.44822*TMath::Power(TMath::Exp(-0.364259*x-TMath::Abs(-0.12213)*x*x)+x/1.42716,-5.37383))",
        "443_pt": "x*3.76783e-05/TMath::Power((1+TMath::Power(x/4.06472,2.0)),3.03429)",
        "321_pt": "1.2778632*x*7.70776*TMath::Power(TMath::Exp(-0.618249*x-TMath::Abs(3.16962e-09)*x*x)+x/1.02821,-5.47764)",
        "2212_pt": "1.2778632*x*1.4891*TMath::Power(TMath::Exp(-0.4799*x-TMath::Abs(0.0225614)*x*x)+x/1.6315,-6.82731)"
    },
    "13TeV_HM_rhoup": {
        "histoMtScaleFactor": {
            "113": 1.044,
            "223": 0.572,
            "331": 0.4
        },
        "111_pt": "( x*(326.754*TMath::Exp(-(TMath::Sqrt(x*x+0.134977*0.134977)-0.134977)/0.140039)+17.4259*TMath::Power(1+(x*x)/(0.685364*0.685364*2.88243),-2.88243)) )",
        "221_pt": "( x*(326.754*TMath::Exp(-(TMath::Sqrt(x*x+0.134977*0.134977)-0.134977)/0.140039)+17.4259*TMath::Power(1+(x*x)/(0.685364*0.685364*2.88243),-2.88243)) ) *   ((0.691819*1.)+(180.263*(-0.00350264*TMath::Power(1.+((x/0.91991)*(x/0.91991)),-(0.242107)))))/(1.+(-0.00350264*TMath::Power(1.+((x/0.91991)*(x/0.91991)),-(0.242107))))",
        "333_pt": "(1.217*x*0.44822*TMath::Power(TMath::Exp(-0.364259*x-TMath::Abs(-0.12213)*x*x)+x/1.42716,-5.37383))",
        "443_pt": "x*3.76783e-05/TMath::Power((1+TMath::Power(x/4.06472,2.0)),3.03429)",
        "321_pt": "1.2778632*x*7.70776*TMath::Power(TMath::Exp(-0.618249*x-TMath::Abs(3.16962e-09)*x*x)+x/1.02821,-5.47764)",
        "2212_pt": "1.2778632*x*1.4891*TMath::Power(TMath::Exp(-0.4799*x-TMath::Abs(0.0225614)*x*x)+x/1.6315,-6.82731)"
    },
    "13TeV_HM_rhodown": {
        "histoMtScaleFactor": {
            "113": 0.696,
            "223": 0.572,
            "331": 0.4
        },
        "111_pt": "( x*(326.754*TMath::Exp(-(TMath::Sqrt(x*x+0.134977*0.134977)-0.134977)/0.140039)+17.4259*TMath::Power(1+(x*x)/(0.685364*0.685364*2.88243),-2.88243)) )",
        "221_pt": "( x*(326.754*TMath::Exp(-(TMath::Sqrt(x*x+0.134977*0.134977)-0.134977)/0.140039)+17.4259*TMath::Power(1+(x*x)/(0.685364*0.685364*2.88243),-2.88243)) ) *   ((0.691819*1.)+(180.263*(-0.00350264*TMath::Power(1.+((x/0.91991)*(x/0.91991)),-(0.242107)))))/(1.+(-0.00350264*TMath::Power(1.+((x/0.91991)*(x/0.91991)),-(0.242107))))",
        "333_pt": "(1.217*x*0.44822*TMath::Power(TMath::Exp(-0.364259*x-TMath::Abs(-0.12213)*x*x)+x/1.42716,-5.37383))",
        "443_pt": "x*3.76783e-05/TMath::Power((1+TMath::Power(x/4.06472,2.0)),3.03429)",
        "321_pt": "1.2778632*x*7.70776*TMath::Power(TMath::Exp(-0.618249*x-TMath::Abs(3.16962e-09)*x*x)+x/1.02821,-5.47764)",
        "2212_pt": "1.2778632*x*1.4891*TMath::Power(TMath::Exp(-0.4799*x-TMath::Abs(0.0225614)*x*x)+x/1.6315,-6.82731)"
    },
    "13TeV_HM_omegaup": {
        "histoMtScaleFactor": {
            "113": 0.87,
            "223": 0.6864,
            "331": 0.4
        },
        "111_pt": "( x*(326.754*TMath::Exp(-(TMath::Sqrt(x*x+0.134977*0.134977)-0.134977)/0.140039)+17.4259*TMath::Power(1+(x*x)/(0.685364*0.685364*2.88243),-2.88243)) )",
        "221_pt": "( x*(326.754*TMath::Exp(-(TMath::Sqrt(x*x+0.134977*0.134977)-0.134977)/0.140039)+17.4259*TMath::Power(1+(x*x)/(0.685364*0.685364*2.88243),-2.88243)) ) *   ((0.691819*1.)+(180.263*(-0.00350264*TMath::Power(1.+((x/0.91991)*(x/0.91991)),-(0.242107)))))/(1.+(-0.00350264*TMath::Power(1.+((x/0.91991)*(x/0.91991)),-(0.242107))))",
        "333_pt": "(1.217*x*0.44822*TMath::Power(TMath::Exp(-0.364259*x-TMath::Abs(-0.12213)*x*x)+x/1.42716,-5.37383))",
        "443_pt": "x*3.76783e-05/TMath::Power((1+TMath::Power(x/4.06472,2.0)),3.03429)",
        "321_pt": "1.2778632*x*7.70776*TMath::Power(TMath::Exp(-0.618249*x-TMath::Abs(3.16962e-09)*x*x)+x/1.02821,-5.47764)",
        "2212_pt": "1.2778632*x*1.4891*TMath::Power(TMath::Exp(-0.4799*x-TMath::Abs(0.0225614)*x*x)+x/1.6315,-6.82731)"
    },
    "13TeV_HM_omegadown": {
        "histoMtScaleFactor": {
            "113": 0.87,
            "223": 0.4576,
            "331": 0.4
        },
        "111_pt": "( x*(326.754*TMath::Exp(-(TMath::Sqrt(x*x+0.134977*0.134977)-0.134977)/0.140039)+17.4259*TMath::Power(1+(x*x)/(0.685364*0.685364*2.88243),-2.88243)) )",
        "221_pt": "( x*(326.754*TMath::Exp(-(TMath::Sqrt(x*x+0.134977*0.134977)-0.134977)/0.140039)+17.4259*TMath::Power(1+(x*x)/(0.685364*0.685364*2.88243),-2.88243)) ) *   ((0.691819*1.)+(180.263*(-0.00350264*TMath::Power(1.+((x/0.91991)*(x/0.91991)),-(0.242107)))))/(1.+(-0.00350264*TMath::Power(1.+((x/0.91991)*(x/0.91991)),-(0.242107))))",
        "333_pt": "(1.217*x*0.44822*TMath::Power(TMath::Exp(-0.364259*x-TMath::Abs(-0.12213)*x*x)+x/1.42716,-5.37383))",
        "443_pt": "x*3.76783e-05/TMath::Power((1+TMath::Power(x/4.06472,2.0)),3.03429)",
        "321_pt": "1.2778632*x*7.70776*TMath::Power(TMath::Exp(-0.618249*x-TMath::Abs(3.16962e-09)*x*x)+x/1.02821,-5.47764)",
        "2212_pt": "1.2778632*x*1.4891*TMath::Power(TMath::Exp(-0.4799*x-TMath::Abs(0.0225614)*x*x)+x/1.6315,-6.82731)"
    },
    "13TeV_HM_default_ptlimit": {
        "histoMtScaleFactor": {
            "113": 0.87,
            "223": 0.572,
            "331": 0.4
        },
        "111_pt": "( x*(326.754*TMath::Exp(-(TMath::Sqrt(x*x+0.134977*0.134977)-0.134977)/0.140039)+17.4259*TMath::Power(1+(x*x)/(0.685364*0.685364*2.88243),-2.88243)) )",
        "221_pt": "( x*(204.529*TMath::Exp(-(TMath::Sqrt(x*x+0.134977*0.134977)-0.134977)/0.155686)+14.9262*TMath::Power(1+(x*x)/(0.704871*0.704871*2.90918),-2.90918)) ) *  ((1.16587*1.)+(255.088*(-0.00446422*TMath::Power(1.+((x/0.561068)*(x/0.561068)),-(0.0952805)))))/(1.+(-0.00446422*TMath::Power(1.+((x/0.561068)*(x/0.561068)),-(0.0952805)))) ",
        "333_pt": "(1.217*x*0.44822*TMath::Power(TMath::Exp(-0.364259*x-TMath::Abs(-0.12213)*x*x)+x/1.42716,-5.37383))",
        "443_pt": "x*3.76783e-05/TMath::Power((1+TMath::Power(x/4.06472,2.0)),3.03429)",
        "321_pt": "1.2778632*x*7.70776*TMath::Power(TMath::Exp(-0.618249*x-TMath::Abs(3.16962e-09)*x*x)+x/1.02821,-5.47764)",
        "2212_pt": "1.2778632*x*1.4891*TMath::Power(TMath::Exp(-0.4799*x-TMath::Abs(0.0225614)*x*x)+x/1.6315,-6.82731)"
    },
    "13TeV_HM_etaup_ptlimit": {
        "histoMtScaleFactor": {
            "113": 0.87,
            "223": 0.572,
            "331": 0.4
        },
        "111_pt": "( x*(326.754*TMath::Exp(-(TMath::Sqrt(x*x+0.134977*0.134977)-0.134977)/0.140039)+17.4259*TMath::Power(1+(x*x)/(0.685364*0.685364*2.88243),-2.88243)) )",
        "221_pt": "( x*(204.529*TMath::Exp(-(TMath::Sqrt(x*x+0.134977*0.134977)-0.134977)/0.155686)+14.9262*TMath::Power(1+(x*x)/(0.704871*0.704871*2.90918),-2.90918)) ) *  ((2.05473*1.)+(339.781*(-0.00588883*TMath::Power(1.+((x/0.574557)*(x/0.574557)),-(0.0482478)))))/(1.+(-0.00588883*TMath::Power(1.+((x/0.574557)*(x/0.574557)),-(0.0482478)))) ",
        "333_pt": "(1.217*x*0.44822*TMath::Power(TMath::Exp(-0.364259*x-TMath::Abs(-0.12213)*x*x)+x/1.42716,-5.37383))",
        "443_pt": "x*3.76783e-05/TMath::Power((1+TMath::Power(x/4.06472,2.0)),3.03429)",
        "321_pt": "1.2778632*x*7.70776*TMath::Power(TMath::Exp(-0.618249*x-TMath::Abs(3.16962e-09)*x*x)+x/1.02821,-5.47764)",
        "2212_pt": "1.2778632*x*1.4891*TMath::Power(TMath::Exp(-0.4799*x-TMath::Abs(0.0225614)*x*x)+x/1.6315,-6.82731)"
    },
    "13TeV_HM_etadown_ptlimit": {
        "histoMtScaleFactor": {
            "113": 0.87,
            "223": 0.572,
            "331": 0.4
        },
        "111_pt": "( x*(326.754*TMath::Exp(-(TMath::Sqrt(x*x+0.134977*0.134977)-0.134977)/0.140039)+17.4259*TMath::Power(1+(x*x)/(0.685364*0.685364*2.88243),-2.88243)) )",
        "221_pt": "( x*(204.529*TMath::Exp(-(TMath::Sqrt(x*x+0.134977*0.134977)-0.134977)/0.155686)+14.9262*TMath::Power(1+(x*x)/(0.704871*0.704871*2.90918),-2.90918)) ) *  ((0.810298*1.)+(214.309*(-0.0037561*TMath::Power(1.+((x/0.590486)*(x/0.590486)),-(0.157333)))))/(1.+(-0.0037561*TMath::Power(1.+((x/0.590486)*(x/0.590486)),-(0.157333)))) ",
        "333_pt": "(1.217*x*0.44822*TMath::Power(TMath::Exp(-0.364259*x-TMath::Abs(-0.12213)*x*x)+x/1.42716,-5.37383))",
        "443_pt": "x*3.76783e-05/TMath::Power((1+TMath::Power(x/4.06472,2.0)),3.03429)",
        "321_pt": "1.2778632*x*7.70776*TMath::Power(TMath::Exp(-0.618249*x-TMath::Abs(3.16962e-09)*x*x)+x/1.02821,-5.47764)",
        "2212_pt": "1.2778632*x*1.4891*TMath::Power(TMath::Exp(-0.4799*x-TMath::Abs(0.0225614)*x*x)+x/1.6315,-6.82731)"
    },
    "13TeV_HM_Prelim_default": {
        "histoMtScaleFactor": {
            "113": 0.87,
            "223": 0.572,
            "331": 0.4
        },
        "111_pt": "( x*(302.631*TMath::Exp(-(TMath::Sqrt(x*x+0.134977*0.134977)-0.134977)/0.144834)+16.3521*TMath::Power(1+(x*x)/(0.696618*0.696618*2.89513),-2.89513)) )",
        "221_pt": "( x*(302.631*TMath::Exp(-(TMath::Sqrt(x*x+0.134977*0.134977)-0.134977)/0.144834)+16.3521*TMath::Power(1+(x*x)/(0.696618*0.696618*2.89513),-2.89513)) ) *   ((0.691819*1.)+(180.263*(-0.00350264*TMath::Power(1.+((x/0.91991)*(x/0.91991)),-(0.242107)))))/(1.+(-0.00350264*TMath::Power(1.+((x/0.91991)*(x/0.91991)),-(0.242107))))",
        "333_pt": "(1.217*x*0.44822*TMath::Power(TMath::Exp(-0.364259*x-TMath::Abs(-0.12213)*x*x)+x/1.42716,-5.37383))",
        "443_pt": "x*3.76783e-05/TMath::Power((1+TMath::Power(x/4.06472,2.0)),3.03429)",
        "321_pt": "1.2778632*x*7.70776*TMath::Power(TMath::Exp(-0.618249*x-TMath::Abs(3.16962e-09)*x*x)+x/1.02821,-5.47764)",
        "2212_pt": "1.2778632*x*1.4891*TMath::Power(TMath::Exp(-0.4799*x-TMath::Abs(0.0225614)*x*x)+x/1.6315,-6.82731)"
    },
    "13TeV_HM_Prelim_etaup": {
        "histoMtScaleFactor": {
            "113": 0.87,
            "223": 0.572,
            "331": 0.4
        },
        "111_pt": "( x*(302.631*TMath::Exp(-(TMath::Sqrt(x*x+0.134977*0.134977)-0.134977)/0.144834)+16.3521*TMath::Power(1+(x*x)/(0.696618*0.696618*2.89513),-2.89513)) )",
        "221_pt": "( x*(302.631*TMath::Exp(-(TMath::Sqrt(x*x+0.134977*0.134977)-0.134977)/0.144834)+16.3521*TMath::Power(1+(x*x)/(0.696618*0.696618*2.89513),-2.89513)) ) *   ((0.799845*1.)+(192.141*(-0.00373188*TMath::Power(1.+((x/0.953155)*(x/0.953155)),-(0.199252)))))/(1.+(-0.00373188*TMath::Power(1.+((x/0.953155)*(x/0.953155)),-(0.199252))))",
        "333_pt": "(1.217*x*0.44822*TMath::Power(TMath::Exp(-0.364259*x-TMath::Abs(-0.12213)*x*x)+x/1.42716,-5.37383))",
        "443_pt": "x*3.76783e-05/TMath::Power((1+TMath::Power(x/4.06472,2.0)),3.03429)",
        "321_pt": "1.2778632*x*7.70776*TMath::Power(TMath::Exp(-0.618249*x-TMath::Abs(3.16962e-09)*x*x)+x/1.02821,-5.47764)",
        "2212_pt": "1.2778632*x*1.4891*TMath::Power(TMath::Exp(-0.4799*x-TMath::Abs(0.0225614)*x*x)+x/1.6315,-6.82731)"
    },
    "13TeV_HM_Prelim_etadown": {
        "histoMtScaleFactor": {
            "113": 0.87,
            "223": 0.572,
            "331": 0.4
        },
        "111_pt": "( x*(302.631*TMath::Exp(-(TMath::Sqrt(x*x+0.134977*0.134977)-0.134977)/0.144834)+16.3521*TMath::Power(1+(x*x)/(0.696618*0.696618*2.89513),-2.89513)) )",
        "221_pt": "( x*(302.631*TMath::Exp(-(TMath::Sqrt(x*x+0.134977*0.134977)-0.134977)/0.144834)+16.3521*TMath::Power(1+(x*x)/(0.696618*0.696618*2.89513),-2.89513)) ) *   ((0.60826*1.)+(171.512*(-0.00333377*TMath::Power(1.+((x/0.891623)*(x/0.891623)),-(0.289837)))))/(1.+(-0.00333377*TMath::Power(1.+((x/0.891623)*(x/0.891623)),-(0.289837))))",
        "333_pt": "(1.217*x*0.44822*TMath::Power(TMath::Exp(-0.364259*x-TMath::Abs(-0.12213)*x*x)+x/1.42716,-5.37383))",
        "443_pt": "x*3.76783e-05/TMath::Power((1+TMath::Power(x/4.06472,2.0)),3.03429)",
        "321_pt": "1.2778632*x*7.70776*TMath::Power(TMath::Exp(-0.618249*x-TMath::Abs(3.16962e-09)*x*x)+x/1.02821,-5.47764)",
        "2212_pt": "1.2778632*x*1.4891*TMath::Power(TMath::Exp(-0.4799*x-TMath::Abs(0.0225614)*x*x)+x/1.6315,-6.82731)"
    },
    "13TeV_HM_Prelim_pi0up_eta": {
        "histoMtScaleFactor": {
            "113": 0.87,
            "223": 0.572,
            "331": 0.4
        },
        "111_pt": "( x*(302.631*TMath::Exp(-(TMath::Sqrt(x*x+0.134977*0.134977)-0.134977)/0.144834)+16.3521*TMath::Power(1+(x*x)/(0.696618*0.696618*2.89513),-2.89513)) )",
        "221_pt": "( x*(458.576*TMath::Exp(-(TMath::Sqrt(x*x+0.134977*0.134977)-0.134977)/0.132629)+18.7291*TMath::Power(1+(x*x)/(0.680161*0.680161*2.87203),-2.87203)) ) *   ((0.691819*1.)+(180.263*(-0.00350264*TMath::Power(1.+((x/0.91991)*(x/0.91991)),-(0.242107)))))/(1.+(-0.00350264*TMath::Power(1.+((x/0.91991)*(x/0.91991)),-(0.242107))))",
        "333_pt": "(1.217*x*0.44822*TMath::Power(TMath::Exp(-0.364259*x-TMath::Abs(-0.12213)*x*x)+x/1.42716,-5.37383))",
        "443_pt": "x*3.76783e-05/TMath::Power((1+TMath::Power(x/4.06472,2.0)),3.03429)",
        "321_pt": "1.2778632*x*7.70776*TMath::Power(TMath::Exp(-0.618249*x-TMath::Abs(3.16962e-09)*x*x)+x/1.02821,-5.47764)",
        "2212_pt": "1.2778632*x*1.4891*TMath::Power(TMath::Exp(-0.4799*x-TMath::Abs(0.0225614)*x*x)+x/1.6315,-6.82731)"
    },
    "13TeV_HM_Prelim_pi0up_etaup": {
        "histoMtScaleFactor": {
            "113": 0.87,
            "223": 0.572,
            "331": 0.4
        },
        "111_pt": "( x*(302.631*TMath::Exp(-(TMath::Sqrt(x*x+0.134977*0.134977)-0.134977)/0.144834)+16.3521*TMath::Power(1+(x*x)/(0.696618*0.696618*2.89513),-2.89513)) )",
        "221_pt": "( x*(458.576*TMath::Exp(-(TMath::Sqrt(x*x+0.134977*0.134977)-0.134977)/0.132629)+18.7291*TMath::Power(1+(x*x)/(0.680161*0.680161*2.87203),-2.87203)) ) *   ((0.799845*1.)+(192.141*(-0.00373188*TMath::Power(1.+((x/0.953155)*(x/0.953155)),-(0.199252)))))/(1.+(-0.00373188*TMath::Power(1.+((x/0.953155)*(x/0.953155)),-(0.199252))))",
        "333_pt": "(1.217*x*0.44822*TMath::Power(TMath::Exp(-0.364259*x-TMath::Abs(-0.12213)*x*x)+x/1.42716,-5.37383))",
        "443_pt": "x*3.76783e-05/TMath::Power((1+TMath::Power(x/4.06472,2.0)),3.03429)",
        "321_pt": "1.2778632*x*7.70776*TMath::Power(TMath::Exp(-0.618249*x-TMath::Abs(3.16962e-09)*x*x)+x/1.02821,-5.47764)",
        "2212_pt": "1.2778632*x*1.4891*TMath::Power(TMath::Exp(-0.4799*x-TMath::Abs(0.0225614)*x*x)+x/1.6315,-6.82731)"
    },
    "13TeV_HM_Prelim_pi0up_etadown": {
        "histoMtScaleFactor": {
            "113": 0.87,
            "223": 0.572,
            "331": 0.4
        },
        "111_pt": "( x*(302.631*TMath::Exp(-(TMath::Sqrt(x*x+0.134977*0.134977)-0.134977)/0.144834)+16.3521*TMath::Power(1+(x*x)/(0.696618*0.696618*2.89513),-2.89513)) )",
        "221_pt": "( x*(458.576*TMath::Exp(-(TMath::Sqrt(x*x+0.134977*0.134977)-0.134977)/0.132629)+18.7291*TMath::Power(1+(x*x)/(0.680161*0.680161*2.87203),-2.87203)) ) *   ((0.60826*1.)+(171.512*(-0.00333377*TMath::Power(1.+((x/0.891623)*(x/0.891623)),-(0.289837)))))/(1.+(-0.00333377*TMath::Power(1.+((x/0.891623)*(x/0.891623)),-(0.289837))))",
        "333_pt": "(1.217*x*0.44822*TMath::Power(TMath::Exp(-0.364259*x-TMath::Abs(-0.12213)*x*x)+x/1.42716,-5.37383))",
        "443_pt": "x*3.76783e-05/TMath::Power((1+TMath::Power(x/4.06472,2.0)),3.03429)",
        "321_pt": "1.2778632*x*7.70776*TMath::Power(TMath::Exp(-0.618249*x-TMath::Abs(3.16962e-09)*x*x)+x/1.02821,-5.47764)",
        "2212_pt": "1.2778632*x*1.4891*TMath::Power(TMath::Exp(-0.4799*x-TMath::Abs(0.0225614)*x*x)+x/1.6315,-6.82731)"
    },
    "13TeV_HM_Prelim_pi0down_eta": {
        "histoMtScaleFactor": {
            "113": 0.87,
            "223": 0.572,
            "331": 0.4
        },
        "111_pt": "( x*(302.631*TMath::Exp(-(TMath::Sqrt(x*x+0.134977*0.134977)-0.134977)/0.144834)+16.3521*TMath::Power(1+(x*x)/(0.696618*0.696618*2.89513),-2.89513)) )",
        "221_pt": "( x*(190.467*TMath::Exp(-(TMath::Sqrt(x*x+0.134977*0.134977)-0.134977)/0.161605)+13.8504*TMath::Power(1+(x*x)/(0.718129*0.718129*2.92313),-2.92313)) ) *   ((0.691819*1.)+(180.263*(-0.00350264*TMath::Power(1.+((x/0.91991)*(x/0.91991)),-(0.242107)))))/(1.+(-0.00350264*TMath::Power(1.+((x/0.91991)*(x/0.91991)),-(0.242107))))",
        "333_pt": "(1.217*x*0.44822*TMath::Power(TMath::Exp(-0.364259*x-TMath::Abs(-0.12213)*x*x)+x/1.42716,-5.37383))",
        "443_pt": "x*3.76783e-05/TMath::Power((1+TMath::Power(x/4.06472,2.0)),3.03429)",
        "321_pt": "1.2778632*x*7.70776*TMath::Power(TMath::Exp(-0.618249*x-TMath::Abs(3.16962e-09)*x*x)+x/1.02821,-5.47764)",
        "2212_pt": "1.2778632*x*1.4891*TMath::Power(TMath::Exp(-0.4799*x-TMath::Abs(0.0225614)*x*x)+x/1.6315,-6.82731)"
    },
    "13TeV_HM_Prelim_pi0down_etaup": {
        "histoMtScaleFactor": {
            "113": 0.87,
            "223": 0.572,
            "331": 0.4
        },
        "111_pt": "( x*(302.631*TMath::Exp(-(TMath::Sqrt(x*x+0.134977*0.134977)-0.134977)/0.144834)+16.3521*TMath::Power(1+(x*x)/(0.696618*0.696618*2.89513),-2.89513)) )",
        "221_pt": "( x*(190.467*TMath::Exp(-(TMath::Sqrt(x*x+0.134977*0.134977)-0.134977)/0.161605)+13.8504*TMath::Power(1+(x*x)/(0.718129*0.718129*2.92313),-2.92313)) ) *   ((0.799845*1.)+(192.141*(-0.00373188*TMath::Power(1.+((x/0.953155)*(x/0.953155)),-(0.199252)))))/(1.+(-0.00373188*TMath::Power(1.+((x/0.953155)*(x/0.953155)),-(0.199252))))",
        "333_pt": "(1.217*x*0.44822*TMath::Power(TMath::Exp(-0.364259*x-TMath::Abs(-0.12213)*x*x)+x/1.42716,-5.37383))",
        "443_pt": "x*3.76783e-05/TMath::Power((1+TMath::Power(x/4.06472,2.0)),3.03429)",
        "321_pt": "1.2778632*x*7.70776*TMath::Power(TMath::Exp(-0.618249*x-TMath::Abs(3.16962e-09)*x*x)+x/1.02821,-5.47764)",
        "2212_pt": "1.2778632*x*1.4891*TMath::Power(TMath::Exp(-0.4799*x-TMath::Abs(0.0225614)*x*x)+x/1.6315,-6.82731)"
    },
    "13TeV_HM_Prelim_pi0down_etadown": {
        "histoMtScaleFactor": {
            "113": 0.87,
            "223": 0.572,
            "331": 0.4
        },
        "111_pt": "( x*(302.631*TMath::Exp(-(TMath::Sqrt(x*x+0.134977*0.134977)-0.134977)/0.144834)+16.3521*TMath::Power(1+(x*x)/(0.696618*0.696618*2.89513),-2.89513)) )",
        "221_pt": "( x*(190.467*TMath::Exp(-(TMath::Sqrt(x*x+0.134977*0.134977)-0.134977)/0.161605)+13.8504*TMath::Power(1+(x*x)/(0.718129*0.718129*2.92313),-2.92313)) ) *   ((0.60826*1.)+(171.512*(-0.00333377*TMath::Power(1.+((x/0.891623)*(x/0.891623)),-(0.289837)))))/(1.+(-0.00333377*TMath::Power(1.+((x/0.891623)*(x/0.891623)),-(0.289837))))",
        "333_pt": "(1.217*x*0.44822*TMath::Power(TMath::Exp(-0.364259*x-TMath::Abs(-0.12213)*x*x)+x/1.42716,-5.37383))",
        "443_pt": "x*3.76783e-05/TMath::Power((1+TMath::Power(x/4.06472,2.0)),3.03429)",
        "321_pt": "1.2778632*x*7.70776*TMath::Power(TMath::Exp(-0.618249*x-TMath::Abs(3.16962e-09)*x*x)+x/1.02821,-5.47764)",
        "2212_pt": "1.2778632*x*1.4891*TMath::Power(TMath::Exp(-0.4799*x-TMath::Abs(0.0225614)*x*x)+x/1.6315,-6.82731)"
    },
    "13TeV_HM_pi0_CPextra1": {
        "histoMtScaleFactor": {
            "113": 0.87,
            "223": 0.572,
            "331": 0.4
        },
        "111_pt": "( x*(269.338*TMath::Exp(-(TMath::Sqrt(x*x+0.134977*0.134977)-0.134977)/0.0845415)+47.3995*TMath::Power(1+(x*x)/(0.549138*0.549138*2.80868),-2.80868)) ) *   ((0.691819*1.)+(180.263*(-0.00350264*TMath::Power(1.+((x/0.91991)*(x/0.91991)),-(0.242107)))))/(1.+(-0.00350264*TMath::Power(1.+((x/0.91991)*(x/0.91991)),-(0.242107))))",
        "221_pt": "( x*(326.754*TMath::Exp(-(TMath::Sqrt(x*x+0.134977*0.134977)-0.134977)/0.140039)+17.4259*TMath::Power(1+(x*x)/(0.685364*0.685364*2.88243),-2.88243)) ) *   ((0.691819*1.)+(180.263*(-0.00350264*TMath::Power(1.+((x/0.91991)*(x/0.91991)),-(0.242107)))))/(1.+(-0.00350264*TMath::Power(1.+((x/0.91991)*(x/0.91991)),-(0.242107))))",
        "333_pt": "(1.217*x*0.44822*TMath::Power(TMath::Exp(-0.364259*x-TMath::Abs(-0.12213)*x*x)+x/1.42716,-5.37383))",
        "443_pt": "x*3.76783e-05/TMath::Power((1+TMath::Power(x/4.06472,2.0)),3.03429)",
        "321_pt": "1.2778632*x*7.70776*TMath::Power(TMath::Exp(-0.618249*x-TMath::Abs(3.16962e-09)*x*x)+x/1.02821,-5.47764)",
        "2212_pt": "1.2778632*x*1.4891*TMath::Power(TMath::Exp(-0.4799*x-TMath::Abs(0.0225614)*x*x)+x/1.6315,-6.82731)"
    },
    "13TeV_HM_pi0_CPextra2": {
        "histoMtScaleFactor": {
            "113": 0.87,
            "223": 0.572,
            "331": 0.4
        },
        "111_pt": "( x*(319.201*TMath::Exp(-(TMath::Sqrt(x*x+0.134977*0.134977)-0.134977)/0.10158)+35.8138*TMath::Power(1+(x*x)/(0.583998*0.583998*2.82716),-2.82716)) ) *   ((0.691819*1.)+(180.263*(-0.00350264*TMath::Power(1.+((x/0.91991)*(x/0.91991)),-(0.242107)))))/(1.+(-0.00350264*TMath::Power(1.+((x/0.91991)*(x/0.91991)),-(0.242107))))",
        "221_pt": "( x*(326.754*TMath::Exp(-(TMath::Sqrt(x*x+0.134977*0.134977)-0.134977)/0.140039)+17.4259*TMath::Power(1+(x*x)/(0.685364*0.685364*2.88243),-2.88243)) ) *   ((0.691819*1.)+(180.263*(-0.00350264*TMath::Power(1.+((x/0.91991)*(x/0.91991)),-(0.242107)))))/(1.+(-0.00350264*TMath::Power(1.+((x/0.91991)*(x/0.91991)),-(0.242107))))",
        "333_pt": "(1.217*x*0.44822*TMath::Power(TMath::Exp(-0.364259*x-TMath::Abs(-0.12213)*x*x)+x/1.42716,-5.37383))",
        "443_pt": "x*3.76783e-05/TMath::Power((1+TMath::Power(x/4.06472,2.0)),3.03429)",
        "321_pt": "1.2778632*x*7.70776*TMath::Power(TMath::Exp(-0.618249*x-TMath::Abs(3.16962e-09)*x*x)+x/1.02821,-5.47764)",
        "2212_pt": "1.2778632*x*1.4891*TMath::Power(TMath::Exp(-0.4799*x-TMath::Abs(0.0225614)*x*x)+x/1.6315,-6.82731)"
    },
    "13TeV_HM_pi0_CPextra3": {
        "histoMtScaleFactor": {
            "113": 0.87,
            "223": 0.572,
            "331": 0.4
        },
        "111_pt": "( x*(375.238*TMath::Exp(-(TMath::Sqrt(x*x+0.134977*0.134977)-0.134977)/0.110871)+27.7713*TMath::Power(1+(x*x)/(0.617826*0.617826*2.84554),-2.84554)) ) *   ((0.691819*1.)+(180.263*(-0.00350264*TMath::Power(1.+((x/0.91991)*(x/0.91991)),-(0.242107)))))/(1.+(-0.00350264*TMath::Power(1.+((x/0.91991)*(x/0.91991)),-(0.242107))))",
        "221_pt": "( x*(326.754*TMath::Exp(-(TMath::Sqrt(x*x+0.134977*0.134977)-0.134977)/0.140039)+17.4259*TMath::Power(1+(x*x)/(0.685364*0.685364*2.88243),-2.88243)) ) *   ((0.691819*1.)+(180.263*(-0.00350264*TMath::Power(1.+((x/0.91991)*(x/0.91991)),-(0.242107)))))/(1.+(-0.00350264*TMath::Power(1.+((x/0.91991)*(x/0.91991)),-(0.242107))))",
        "333_pt": "(1.217*x*0.44822*TMath::Power(TMath::Exp(-0.364259*x-TMath::Abs(-0.12213)*x*x)+x/1.42716,-5.37383))",
        "443_pt": "x*3.76783e-05/TMath::Power((1+TMath::Power(x/4.06472,2.0)),3.03429)",
        "321_pt": "1.2778632*x*7.70776*TMath::Power(TMath::Exp(-0.618249*x-TMath::Abs(3.16962e-09)*x*x)+x/1.02821,-5.47764)",
        "2212_pt": "1.2778632*x*1.4891*TMath::Power(TMath::Exp(-0.4799*x-TMath::Abs(0.0225614)*x*x)+x/1.6315,-6.82731)"
    }
}
